Workbook

Sheet requests
A1: Key | B1: ticketNo | C1: currentDateTime | D1: employeeId | E1: employeeName | F1: Plant | G1: userId | H1: jobType | I1: issueType | J1: อาการ | K1: ระบุ | L1: displayName | M1: pictureUrl | N1: request | O1: vncNumber | P1: Phonenum | Q1: FileAttachmentURL | R1: Status | S1: reply | T1: photo | U1: admin | V1: โลเคชั่นที่พบปัญหา
A2: 1 | B2: IT2410-001 | C2: 45572.373 | D2: 31043 | E2: {=XLOOKUP(D2,Employee!A:A,Employee!D:D)&" "&XLOOKUP(D2,Employee!A:A,Employee!E:E)} | F2: ICT | G2: Ueb33c059803cab01248e22ac9c846d8e | H2: ปัญหาโปรแกรม | I2: Microsoft Office (Word, Excel, Power Point) | J2: เปิดโปรแกรมไม่ได้ | L2: JOEY | M2: https://profile.line-scdn.net/0h3OUNMdD5bGB4N3zHDKUSHwhnbwpbRjVyVFQiU0xnZ1YWUH82VgZzUUtgZQBHAyJkXVBxBR1gMVl0JBsGZmGQVH8HMVFEACozXVAmhw | N2: ขณะนี้ notebook ไม่สามารถใช้งาน Excel, PowerPoint ได้ครับ รบกวนทาง IT มาดำเนินการ Reactivate โปรแกรมให้ด้วยนะครับ ขอบคุณครับ ฐานสุข QAC | O2: 192.168.102.206 | R2: ดำเนินการเรียบร้อย | S2: ReActivate | U2: IT03_วี | V2: ก่อนพัฒนา App
A3: 2 | B3: IT2410-002 | C3: 45572.38 | F3: JA | G3: U49989963d98a2bfb7f7a3a9e4d2b6021 | H3: ปัญหาเครือข่าย และอินเทอร์เน็ต | I3: อินเทอร์เน็ต | J3: ขอเชื่อมต่อ WiFi | L3: Armuayyy | M3: https://profile.line-scdn.net/0hjDlciQ_RNWtBGiXCuCxLFDFKNgFia2x5bnooXXEeal16eHNpbn9yXXQabVp9enA7ay8tD30SbVhNCUINX0zJX0YqaFp9LXM4ZH1_jA | N3: คอมไม่เชื่อมไวไฟ ลองเปิดเครื่องหรือ restart แล้วค่ะ | O3: 127.0.0.1 | Q3: https://drive.google.com/file/d/1rwCV6xwk_lQb2HYIWNrAnjMU4Cus-Gks/view?usp=drivesdk | R3: ดำเนินการเรียบร้อย | S3: ใส่รหัส Wifi ให้ใหม่ | U3: IT01_ดุ่ย | V3: ก่อนพัฒนา App
A4: 3 | B4: IT2410-003 | C4: 45572.428 | G4: c50f6693 | H4: ปัญหาเครือข่าย และอินเทอร์เน็ต | I4: อินเทอร์เน็ต | J4: ขอเชื่อมต่อ WiFi | N4: เชื่อมต่อ wifi ให้คุณโอ๋ | R4: ดำเนินการเรียบร้อย | S4: ใส่ Password wifi ให้ใหม่ คุณโอ๋ | U4: IT02_ก๊อต | V4: ก่อนพัฒนา App
A5: 4 | B5: IT2410-004 | C5: 45572.429 | G5: 296f6487 | H5: ขอสิทธิ์เข้าระบบ (ทำใบขอสิทธิ์) | I5: เปลี่ยนแปลงสิทธิ์ (คอมพิวเตอร์) | J5: ขอเปลี่ยนคอม | N5: เปลี่ยนให้คุณโชติกา ชัยมัง | R5: ดำเนินการเรียบร้อย | S5: Set Notebook เปลี่ยนให้คุณโชติกา ชัยมัง Mail wh02@comets | T5: requests_Images/IT2410-006.photo.035054.jpg | U5: IT02_ก๊อต | V5: ก่อนพัฒนา App
A6: 5 | B6: IT2410-005 | C6: 45572.456 | G6: e275f249 | H6: ปัญหาโปรแกรม | I6: Email | J6: ยกเลิกอีเมล | N6: ยกเลิก Account Email | R6: ดำเนินการเรียบร้อย | S6: ยกเลิก Account Email scm05@cometsintertrade.com | T6: requests_Images/IT2410-005.photo.033030.png | U6: IT02_ก๊อต | V6: ก่อนพัฒนา App
A7: 6 | B7: IT2410-006 | C7: 45572.472 | D7: 10594 | E7: {=XLOOKUP(D7,Employee!A:A,Employee!D:D)&" "&XLOOKUP(D7,Employee!A:A,Employee!E:E)} | F7: Comets | G7: U531c51794d7fcb3d37d6e65612cbcd50 | H7: ปัญหาเครือข่าย และอินเทอร์เน็ต | I7: อินเทอร์เน็ต | J7: ขอเชื่อมต่อ WiFi | L7: P | M7: https://profile.line-scdn.net/0hnb6r03nDMU0bCyRx8j9PMmtbMic4emhfN2V5f3kPai0iPiFJNGl5fy0MO3ghaCRMY2kqeCoKZy0XGEYrBV3NeRw7bHwnPHcePmx7qg | N7: โน๊ตบุ๊คเข้า Wi-Fi ไม่ได้ | O7: - | Q7: https://drive.google.com/file/d/1tbku5lE9v4YVYAXRBQGyn0jrtbOdfc_l/view?usp=drivesdk | R7: ดำเนินการเรียบร้อย | S7: นำ notebook เสียบสาย lan แล้ว reboot เครื่อง 1 ครั้ง ใช้งานได้ปกติ | U7: IT02_ก๊อต | V7: ก่อนพัฒนา App
A8: 7 | B8: IT2410-007 | C8: 45572.475 | D8: 11125 | E8: {=XLOOKUP(D8,Employee!A:A,Employee!D:D)&" "&XLOOKUP(D8,Employee!A:A,Employee!E:E)} | F8: Comets | G8: U012bcfe2879ba579bdb7a9e323eefbae | H8: คอมพิวเตอร์ | I8: Notebook | J8: ล็อกอินไม่ได้ | L8: Phosphate 🍂 | M8: https://profile.line-scdn.net/0ha-yF-K1PPgJUPy7sNWBAfSRvPWh3TmcQKg4hZjM3YmVhXyxTf1B4ZmE9NDNuW3wDKAwlYWU5YjBYLElkSmnCNlMPYzNoCHhRcVh05Q | N8: ไม่สามารถเข้ารหัสโน๊ตบุคได้ค่ะ เป็นของคนที่เข้ามาใหม่ค่ะ | R8: ดำเนินการเรียบร้อย | S8: ใส่ Password wi-fi และ New password Pumhq2024 | U8: IT02_ก๊อต | V8: ก่อนพัฒนา App
A9: 8 | B9: IT2410-008 | C9: 45572.483 | D9: 11021 | E9: {=XLOOKUP(D9,Employee!A:A,Employee!D:D)&" "&XLOOKUP(D9,Employee!A:A,Employee!E:E)} | F9: Comets | G9: Ufa11ba9a84ed39a0fad801a6e50027c9 | H9: ปัญหาโปรแกรม | I9: Microsoft Power Bi | J9: อื่นๆ (โปรดระบุ) | K9: รายชื่อผู้ใช้งาน | L9: Beam_i | M9: https://profile.line-scdn.net/0hRGbqVWxXDWhPCB2614xzFz9YDgJseVR6NzpDXS5bA1Fxak4_YWpBW3lYUFx3bUhrZmgQCSldVllDG3oOUV7xXEg4UFlzP0s7am9Hjw | N9: - ขอนำส่งรายชื่อผู้ใช้งาน MS365 : MS17@cometsintertrade0.microsoft.com เนื่องจากมีข้อมูล Sensitive Data และ Power BI อยู่ จึงเรียนแจ้งให้ทางไอทีพิจารณาผู้ใช้งานให้มีแค่ผู้เกี่ยวข้องและทีมบริหารค่ะ 1. เจกิตาน์ บุญเรือง Email : sls01@cometsintertrade.com 2.อภิญญา หนูช่วย Email : Sales03@cometsintertrade.com 3.พิมพ์ผกา ตั้งมั่น Email : sls02@cometsintertrade.com | R9: ดำเนินการเรียบร้อย | S9: ดำเนินการเรียบร้อยแล้วครับ | U9: IT02_ก๊อต | V9: ก่อนพัฒนา App
A10: 9 | B10: IT2410-009 | C10: 45572.567 | D10: 11101 | E10: {=XLOOKUP(D10,Employee!A:A,Employee!D:D)&" "&XLOOKUP(D10,Employee!A:A,Employee!E:E)} | F10: Comets | G10: U9ef7360853b8507b2a15b3c07ce532a3 | H10: ปัญหาโปรแกรม | I10: Microsoft Office (Word, Excel, Power Point) | J10: อื่นๆ (โปรดระบุ) | K10: รีเซ็ท Password | L10: 𝚖𝚞𝚙𝚒𝚖 | M10: https://profile.line-scdn.net/0htKyjy934K2RUEzv_R_JVGyRDKA53YnJ2fXdsBjQVcVBuIW5hfXFjAGUbIgZuc2o1KiJkUDQbd1RYAFwCSkXXUFMjdlVoJG03cXRhgw | N10: รบกวนreset password MS365 user：ms17 mi | O10: 192.168.202.91 | Q10: https://drive.google.com/file/d/1lP2RIcscHqMxM2GBiNyu_HffJFarJLCS/view?usp=drivesdk | R10: ดำเนินการเรียบร้อย | S10: Reset password เรียบร้อยแล้วครับ | U10: IT02_ก๊อต | V10: ก่อนพัฒนา App
A11: 10 | B11: IT2410-010 | C11: 45572.574 | D11: 10998 | E11: {=XLOOKUP(D11,Employee!A:A,Employee!D:D)&" "&XLOOKUP(D11,Employee!A:A,Employee!E:E)} | F11: Comets | G11: U012bcfe2879ba579bdb7a9e323eefbae | H11: ปัญหาโปรแกรม | I11: Email | J11: อื่นๆ (โปรดระบุ) | K11: ตั้งค่า signature | L11: Phosphate 🍂 | M11: https://profile.line-scdn.net/0ha-yF-K1PPgJUPy7sNWBAfSRvPWh3TmcQKg4hZjM3YmVhXyxTf1B4ZmE9NDNuW3wDKAwlYWU5YjBYLElkSmnCNlMPYzNoCHhRcVh05Q | N11: เปลี่ยน signature ในเมล์ไม่ได้ค่ะ | O11: 192.168.202.192 | R11: ดำเนินการเรียบร้อย | S11: ใส่ signature outlook | T11: requests_Images/IT2410-012.photo.070949.png | U11: IT02_ก๊อต | V11: ก่อนพัฒนา App
A12: 11 | B12: IT2410-011 | C12: 45572.649 | G12: 57541fb6 | H12: ปัญหาโปรแกรม | I12: Microsoft Power Bi | J12: ล็อกอิน License | N12: Login power bi | R12: ดำเนินการเรียบร้อย | S12: Login power bi คุณพลอย QC | T12: requests_Images/IT2410-013.photo.083517.jpg | U12: IT02_ก๊อต | V12: ก่อนพัฒนา App
A13: 12 | B13: IT2410-012 | C13: 45572.653 | F13: Comets | G13: U898ef64932b1971d3c511d24772b7760 | H13: ปริ้นเตอร์ | I13: ปริ้นเตอร์อื่นๆ | J13: ปริ้นไม่ออก | L13: เพชร | M13: https://profile.line-scdn.net/0h6qxujkzLaV5VDHlKmMIXISVcajR2fTBMeD8nOmZYM2s_b34JcTkkOjIOMWxrOygPf2J2bWYLYDxZHx44S1qValI8NG9pOy8NcGsjuQ | N13: 1. เครื่องปริ้นสติกเกอร์ใช้งานไม่ได้ 2. เครื่องปริ้นเอกสารกดสั่งปริ้นแล้ว แต่ไม่ขึ้นที่หน้าจอค่ะ | O13: 192.168.202.237 | Q13: https://drive.google.com/file/d/129p5oW90pG3kwezqvM0bADfj1SS85RYC/view?usp=drivesdk | R13: ดำเนินการเรียบร้อย | S13: Add printer label, set account printer 1 | U13: IT02_ก๊อต | V13: ก่อนพัฒนา App
A14: 13 | B14: IT2410-013 | C14: 45572.669 | G14: 4f20285d | H14: ขอสิทธิ์เข้าระบบ (ทำใบขอสิทธิ์) | I14: เปลี่ยนแปลงสิทธิ์ (Driveshare) | J14: ขอเพิ่มสิทธิ์ไฟล์กลาง | N14: Map drive express ของ vps | R14: ดำเนินการเรียบร้อย | S14: ดำเนินการ Map drive express ของ vps และสั่งซื้อเครื่องสำรองไฟใช้งาน | T14: requests_Images/IT2410-013.photo.035736.jpg | U14: IT02_ก๊อต | V14: ก่อนพัฒนา App
A15: 14 | B15: IT2410-014 | C15: 45572.673 | G15: 6ba3d233 | H15: ปัญหาโปรแกรม | I15: ติดตั้งโปรแกรม | J15: ระบุโปรแกรม | K15: โปรแกรมบัญชี | N15: เพิ่มโปรแกรมโปรแกรมบัญชี | R15: ดำเนินการเรียบร้อย | S15: เพิ่มโปรแกรมโปรแกรมบัญชี express ของ vps Notebook คุณเจี๊ยบ | T15: requests_Images/IT2410-014.photo.033843.jpg | U15: IT02_ก๊อต | V15: ก่อนพัฒนา App
A16: 15 | B16: IT2410-015 | C16: 45573.338 | D16: 30398 | E16: ธัญญรัตน์ หิรัญวงษ์ | F16: ICT | G16: U9e19abc838c7c00bd4995b0f827245bd | H16: คอมพิวเตอร์ | I16: Notebook | J16: อื่นๆ (โปรดระบุ) | K16: Touch Pad ใช้งานไม่ได้ | L16: WaWa 와와 🍀🐰🐻 | M16: https://profile.line-scdn.net/0hpt5JLRQTL1sYMz3IrD1RJGhjLDE7QnZJNFVnbXo0IWogUWkIPVQybysyIWkkBGwPM1dgaiU7eG4UIFg9BmXTbx8DcmokBGkIPVRlvA | N16: Touch Pad เครื่อง Lenovo Notebook ใช้งานไม่ได้ | O16: 192.168.102.178 | R16: ดำเนินการเรียบร้อย | S16: อัพเดทไดร์เวอร์ | U16: IT03_วี | V16: ก่อนพัฒนา App
A17: 16 | B17: IT2410-016 | C17: 45573.372 | D17: 20032 | E17: {=XLOOKUP(D17,Employee!A:A,Employee!D:D)&" "&XLOOKUP(D17,Employee!A:A,Employee!E:E)} | F17: JA | G17: Uad5c175c02aae142cc13cc39e7a5e76f | H17: ปัญหาเครือข่าย และอินเทอร์เน็ต | I17: อินเทอร์เน็ต | J17: ขอเชื่อมต่อ WiFi | L17: Benz | M17: https://profile.line-scdn.net/0hu8BXJA9QKhdvITprTZtUaB9xKX1MUHMFE0U1dAogIXMHEGlBRUJgeFkoICNREGVDFBVldwl2ci5jMl1xcXfWI2gRdyZTFmxESkZg8A | N17: เครื่องเชื่อมต่อ wifi บริษัทไม่ได้ครับ | O17: 127.0.0.1 | Q17: https://drive.google.com/file/d/1_yYdnjH5pbVGObUj8FXLWYtbynClzaYn/view?usp=drivesdk | R17: ดำเนินการเรียบร้อย | S17: ใส่ Password wifi ให้ใหม่ | U17: IT02_ก๊อต | V17: ก่อนพัฒนา App
A18: 17 | B18: IT2410-017 | C18: 45573.401 | D18: 11116 | E18: {=XLOOKUP(D18,Employee!A:A,Employee!D:D)&" "&XLOOKUP(D18,Employee!A:A,Employee!E:E)} | F18: Comets | G18: U4a07ad3a08444cf73353bad165aa7f89 | H18: คอมพิวเตอร์ | I18: Notebook | J18: ล็อคอินไม่ได้ | L18: PCM06_Fyne | M18: https://profile.line-scdn.net/0h3oXNBCvFbEB1N3zGSMESPwVnbypWRjVSCwN0LkgyZyJIVyMVDVglJEY1YCdIBCJFC1lxc0NiZXZ5JBsma2GQdHIHMXFJACoTUFAmpw | N18: ล็อคอินไม่ได้ | Q18: https://drive.google.com/file/d/15zb604qu2Nwp0edWXHYfe6FhsaIZlD3z/view?usp=drivesdk | R18: ดำเนินการเรียบร้อย | S18: Enable account server AD | U18: IT02_ก๊อต | V18: ก่อนพัฒนา App
A19: 18 | B19: IT2410-018 | C19: 45573.401 | D19: 31043 | E19: {=XLOOKUP(D19,Employee!A:A,Employee!D:D)&" "&XLOOKUP(D19,Employee!A:A,Employee!E:E)} | F19: ICT | G19: Ueb33c059803cab01248e22ac9c846d8e | H19: ปริ้นเตอร์ | I19: ปริ้นเตอร์อื่นๆ | J19: ปริ้นไม่ออก | L19: JOEY | M19: https://profile.line-scdn.net/0h3OUNMdD5bGB4N3zHDKUSHwhnbwpbRjVyVFQiU0xnZ1YWUH82VgZzUUtgZQBHAyJkXVBxBR1gMVl0JBsGZmGQVH8HMVFEACozXVAmhw | N19: ขอแจ้งเรื่องเครื่องปริ้นท์ในห้อง QAC ไม่สามารถปริ้นท์งานได้ เบื้องต้นคาดว่ามีปัญหาที่ตัวดึงกระดาษครับ | R19: ดำเนินการเรียบร้อย | S19: ตรวจสอบมีของติดด้านในตัวดึงกระดาษ | U19: IT03_วี | V19: ก่อนพัฒนา App
A20: 19 | B20: IT2410-019 | C20: 45573.446 | D20: 10162 | E20: {=XLOOKUP(D20,Employee!A:A,Employee!D:D)&" "&XLOOKUP(D20,Employee!A:A,Employee!E:E)} | F20: Comets | G20: Ub68788fdfe8d25d25663b7c76638d629 | H20: ขอสิทธิ์เข้าระบบ (ทำใบขอสิทธิ์) | I20: ขอใช้งาน VPN | L20: Yui🌈☀️ | M20: https://profile.line-scdn.net/0hN_0bWV3NEXAdGwHhACJvD21LEho-akhiNCkMRiAbSUZ0LVEmN35XFXhJT0MmLwYkN3QLEyEcGEARCGYWA03tRBorTEEhLFcjOHxblw | N20: เปลี่ยนเครื่องใหม่ต้องการให้เพิ่ม VPN เพื่อใช่งานนอกสถานที่ได้ค่ะ | O20: 112.248 | R20: ดำเนินการเรียบร้อย | S20: Set VPN ใช้งาน | T20: requests_Images/IT2410-021.photo.035147.png | U20: IT02_ก๊อต | V20: ก่อนพัฒนา App
A21: 20 | B21: IT2410-020 | C21: 45573.443 | D21: 10990 | E21: {=XLOOKUP(D21,Employee!A:A,Employee!D:D)&" "&XLOOKUP(D21,Employee!A:A,Employee!E:E)} | F21: Comets | G21: U4f92c5fb937d134192fbe7fe519b545e | H21: อุปกรณ์ไอที | I21: คีย์บอร์ด | J21: อื่นๆ (โปรดระบุ) | K21: เชื่อมคีย์บอร์ดไม่ได้ | L21: กอตอ | M21: https://profile.line-scdn.net/0hyyZv739gJlZ3DzcyF1tYKQdfJTxUfn9EWGg7NUdfKzYeajVXWDs9Y0cIfWMYO2dTW2lrNREIKG97HFEwaVnaYnA_e2dLOGAFUmhssQ | N21: เชื่อมบูลทูธของkeyboardsไม่ได้ เนื่องจากไม่มีตัวรับสัญญาณ | O21: 112.76 | R21: ดำเนินการเรียบร้อย | S21: ส่ง USB Set all-in-one ให้ USER | U21: IT02_ก๊อต | V21: ก่อนพัฒนา App
A22: 21 | B22: IT2410-021 | C22: 45573.461 | D22: 10162 | E22: {=XLOOKUP(D22,Employee!A:A,Employee!D:D)&" "&XLOOKUP(D22,Employee!A:A,Employee!E:E)} | F22: Comets | G22: Ub68788fdfe8d25d25663b7c76638d629 | H22: ปริ้นเตอร์ | I22: ปริ้นเตอร์อื่นๆ | J22: เพิ่มเครื่องปริ้น | L22: Yui🌈☀️ | M22: https://profile.line-scdn.net/0hN_0bWV3NEXAdGwHhACJvD21LEho-akhiNCkMRiAbSUZ0LVEmN35XFXhJT0MmLwYkN3QLEyEcGEARCGYWA03tRBorTEEhLFcjOHxblw | N22: ขอปริ้นเครื่องปริ้น EPSON LQ-310 **VNC112.76 เครื่องหลัก** | O22: 112.248 | R22: ดำเนินการเรียบร้อย | S22: Add share printer EPSON LQ-310 จากเครื่อง CMICT087 | U22: IT02_ก๊อต | V22: ก่อนพัฒนา App
A23: 22 | B23: IT2410-022 | C23: 45573.5 | D23: 90216 | E23: {=XLOOKUP(D23,Employee!A:A,Employee!D:D)&" "&XLOOKUP(D23,Employee!A:A,Employee!E:E)} | F23: Comets | G23: U898ef64932b1971d3c511d24772b7760 | H23: ปัญหาโปรแกรม | I23: Email | J23: เปิดใช้งานอีเมล | L23: เพชร | M23: https://profile.line-scdn.net/0h6qxujkzLaV5VDHlKmMIXISVcajR2fTBMeD8nOmZYM2s_b34JcTkkOjIOMWxrOygPf2J2bWYLYDxZHx44S1qValI8NG9pOy8NcGsjuQ | N23: เพิ่มเมล pcm 31 ให้เครื่องพี่กันหน่อยค่ะ | O23: 192.168.202.237 | R23: ดำเนินการเรียบร้อย | S23: Set account email pcm31@comets | T23: requests_Images/IT2410-024.photo.063248.png | U23: IT02_ก๊อต | V23: ก่อนพัฒนา App
A24: 23 | B24: IT2410-023 | C24: 45573.525 | D24: 11116 | E24: {=XLOOKUP(D24,Employee!A:A,Employee!D:D)&" "&XLOOKUP(D24,Employee!A:A,Employee!E:E)} | F24: Comets | G24: U4a07ad3a08444cf73353bad165aa7f89 | H24: ปริ้นเตอร์ | I24: ปริ้นเตอร์อื่นๆ | J24: เพิ่มเครื่องปริ้น | L24: PCM06_Fyne | M24: https://profile.line-scdn.net/0h3oXNBCvFbEB1N3zGSMESPwVnbypWRjVSCwN0LkgyZyJIVyMVDVglJEY1YCdIBCJFC1lxc0NiZXZ5JBsma2GQdHIHMXFJACoTUFAmpw | N24: 1.รบกวนset up printing1 2. เพิ่ม folder pcm06_11116 ใน ไดร์ฟ Comets procurement ให้ด้วยค่ะ | R24: ดำเนินการเรียบร้อย | S24: Set account printer, Map drive pcm06_11116_Khuanruethai | T24: requests_Images/IT2410-025.photo.062221.png | U24: IT02_ก๊อต | V24: ก่อนพัฒนา App
A25: 24 | B25: IT2410-024 | C25: 45573.595 | D25: 11045 | E25: {=XLOOKUP(D25,Employee!A:A,Employee!D:D)&" "&XLOOKUP(D25,Employee!A:A,Employee!E:E)} | F25: Comets | G25: U398fba6097cdb8f5afd0a164fad81ee9 | H25: ปริ้นเตอร์ | I25: ปริ้นเตอร์ | J25: ขอเช็คสิทธิ์ปริ้นเตอร์ | L25: Saiaew_r | M25: https://profile.line-scdn.net/0hNCXRXjH5EWx1KwHVk7ZvEwV7EgZWWkh-DkRcDxUiTQlAT1JuXEwMAxciRg8YTFE9URgKDEMiGg95OGYKa33tWHIbTF1JHFc_UExbiw | N25: ติดต่อเจ้าหน้าที่ปริ้นเอกสารไม่ได้ ต้องการเช็คสิทธิ์ปริ้นงาน | O25: 78 | R25: ดำเนินการเรียบร้อย | S25: ตรวจสอบ Print Black Impressions 29/300 | T25: requests_Images/IT2410-026.photo.072156.png | U25: IT02_ก๊อต | V25: ก่อนพัฒนา App
A26: 25 | B26: IT2410-025 | C26: 45573.6 | G26: 990cc7f4 | H26: คอมพิวเตอร์ | I26: Notebook | J26: อื่นๆ (โปรดระบุ) | K26: เซ็ทคอมพิวเตอร์ | N26: set computer คุณนะ | R26: ดำเนินการเรียบร้อย | S26: set computer คุณนะ เปลี่ยนจาก macos เป็น computer CMICT085 | U26: IT02_ก๊อต | V26: ก่อนพัฒนา App
A27: 26 | B27: IT2410-026 | C27: 45573.649 | D27: 10162 | E27: {=XLOOKUP(D27,Employee!A:A,Employee!D:D)&" "&XLOOKUP(D27,Employee!A:A,Employee!E:E)} | F27: Comets | G27: Ub68788fdfe8d25d25663b7c76638d629 | H27: ปัญหาโปรแกรม | I27: ติดตั้งโปรแกรม | J27: ระบุโปรแกรม | K27: โปรแกรม Express | L27: Yui🌈☀️ | M27: https://profile.line-scdn.net/0hN_0bWV3NEXAdGwHhACJvD21LEho-akhiNCkMRiAbSUZ0LVEmN35XFXhJT0MmLwYkN3QLEyEcGEARCGYWA03tRBorTEEhLFcjOHxblw | N27: ขอเพิ่มโปรแกรม Express บริษัทขายดี ลงเครื่องค่ะ | O27: 112.248 | R27: ดำเนินการเรียบร้อย | S27: Add express ict ใช้งาน | T27: requests_Images/IT2410-028.photo.084558.png | U27: IT02_ก๊อต | V27: ก่อนพัฒนา App
A28: 27 | B28: IT2410-027 | C28: 45573.659 | G28: caed2e6a | H28: คอมพิวเตอร์ | I28: Macbook | J28: อื่นๆ (โปรดระบุ) | K28: ล็อคอิน Mac OS ไม่ได้ | N28: login Macos ไม่ได้ | R28: ดำเนินการเรียบร้อย | S28: User login Macos ไม่ได้ password ไม่ถูกต้อง repassword ใหม่ | U28: IT02_ก๊อต | V28: ก่อนพัฒนา App
A29: 28 | B29: IT2410-028 | C29: 45573.687 | D29: 11021 | E29: {=XLOOKUP(D29,Employee!A:A,Employee!D:D)&" "&XLOOKUP(D29,Employee!A:A,Employee!E:E)} | F29: Comets | G29: Ufa11ba9a84ed39a0fad801a6e50027c9 | H29: ปัญหาโปรแกรม | I29: Email | J29: อีเมลเต็ม (แบ็คอัพอีเมล) | L29: Beam_i | M29: https://profile.line-scdn.net/0hRGbqVWxXDWhPCB2614xzFz9YDgJseVR6NzpDXS5bA1Fxak4_YWpBW3lYUFx3bUhrZmgQCSldVllDG3oOUV7xXEg4UFlzP0s7am9Hjw | N29: 1.ติดตั้งโปรแกรม Power BI 2.Backup mail | O29: 192.168.203.23 | R29: ดำเนินการเรียบร้อย | S29: ทำการติดตั้งเรียบร้อยแล้ว | U29: IT01_ดุ่ย | V29: ก่อนพัฒนา App
A30: 29 | B30: IT2410-029 | C30: 45574.413 | D30: 10485 | E30: {=XLOOKUP(D30,Employee!A:A,Employee!D:D)&" "&XLOOKUP(D30,Employee!A:A,Employee!E:E)} | F30: Comets | G30: Uee02c5e5492c8399c0f0e2ba134eb675 | H30: คอมพิวเตอร์ | I30: iMac | J30: อื่นๆ (โปรดระบุ) | K30: ยืมเครื่อง iMac ส่งไป ICT | L30: AUMIRABLE | M30: https://profile.line-scdn.net/0htg4tlwjGK0gZDTtcnXVVN2ldKCI6fHJaNWpifSgPdX8hNW9OMzg3Jy9ZJ3slP2wfYT5jKykIJn0VHlwuB1vXfB49dnklOm0bPGphrw | N30: ขอยืมเครื่อง iMac ไปสลับกับเครื่องโน๊ตบุคของน้องกิ่ง mkt ict | Q30: https://drive.google.com/file/d/1s9ELAnBO3OZbywSE3aA8ZtognpdjC-_5/view?usp=drivesdk | R30: ดำเนินการเรียบร้อย | S30: นำส่ง iMac ไป ict ที่คุณกิ่ง mkt ใช้งาน | T30: requests_Images/IT2410-031.photo.033446.jpg | U30: IT01_ดุ่ย | V30: ก่อนพัฒนา App
A31: 30 | B31: IT2410-030 | C31: 45574.415 | D31: 11116 | E31: {=XLOOKUP(D31,Employee!A:A,Employee!D:D)&" "&XLOOKUP(D31,Employee!A:A,Employee!E:E)} | F31: Comets | G31: U4a07ad3a08444cf73353bad165aa7f89 | H31: ปัญหาโปรแกรม | I31: PDF | J31: ตั้งค่าโปรแกรม | L31: PCM06_Fyne | M31: https://profile.line-scdn.net/0h3oXNBCvFbEB1N3zGSMESPwVnbypWRjVSCwN0LkgyZyJIVyMVDVglJEY1YCdIBCJFC1lxc0NiZXZ5JBsma2GQdHIHMXFJACoTUFAmpw | N31: Sign in PDF ไม่ได้ | R31: ดำเนินการเรียบร้อย | S31: add bookmark this tab website sap ดำเนินการเสร็จเรียบร้อยแล้ว, Sign in PDF ไม่ได้ ใช้งานแก้ไข (รอใบขอสิทธิ์ใช้งาน) | U31: IT02_ก๊อต | V31: ก่อนพัฒนา App
A32: 31 | B32: IT2410-031 | C32: 45574.443 | D32: 11084 | E32: {=XLOOKUP(D32,Employee!A:A,Employee!D:D)&" "&XLOOKUP(D32,Employee!A:A,Employee!E:E)} | F32: Comets | G32: Uf549acc1ece2b7a22b35dbbe9d6ef113 | H32: ปัญหาโปรแกรม | I32: โปรแกรมอื่นๆ (โปรดระบุ) | J32: โปรดระบุ | L32: PUR06_โบว์ | M32: https://profile.line-scdn.net/0h8ni4YV7GZ0FETXe2hh0ZPjQdZCtnPD5TPC0hIyQYPiZ4L3RFPXkpJnUaP3IrdCAUbCJ8JyFIP3hIXhAnWhubdUN9OnB4eiESYSotpg | N32: หน้าจอกดไม่ได้ | O32: 100002026 | Q32: https://drive.google.com/file/d/1v-mdIHjnNJfpH_CbW51pY45ilJsSugB4/view?usp=drivesdk | R32: ดำเนินการเรียบร้อย | S32: Reset password user บน AD | U32: IT02_ก๊อต | V32: ก่อนพัฒนา App
A33: 32 | B33: IT2410-032 | C33: 45574.465 | D33: 11125 | E33: {=XLOOKUP(D33,Employee!A:A,Employee!D:D)&" "&XLOOKUP(D33,Employee!A:A,Employee!E:E)} | F33: Comets | G33: U898ef64932b1971d3c511d24772b7760 | H33: ขอสิทธิ์เข้าระบบ (ทำใบขอสิทธิ์) | I33: เปลี่ยนแปลงสิทธิ์ (Driveshare) | J33: ขอเพิ่มสิทธิ์ไฟล์กลาง | L33: เพชร | M33: https://profile.line-scdn.net/0h6qxujkzLaV5VDHlKmMIXISVcajR2fTBMeD8nOmZYM2s_b34JcTkkOjIOMWxrOygPf2J2bWYLYDxZHx44S1qValI8NG9pOy8NcGsjuQ | N33: แมทไดร์ฟ Admin ให้ PCM 33 | O33: 192.168.203.68 | R33: ดำเนินการเรียบร้อย | S33: Map drive 4_PCM PCM32_admin เพื่อใช้งาน share drive ของ admin ตามใบขอสิทธิ์ใช้งาน | T33: requests_Images/IT2410-034.photo.035752.jpg | U33: IT02_ก๊อต | V33: ก่อนพัฒนา App
A34: 33 | B34: IT2410-033 | C34: 45574.468 | D34: 11107 | E34: {=XLOOKUP(D34,Employee!A:A,Employee!D:D)&" "&XLOOKUP(D34,Employee!A:A,Employee!E:E)} | F34: Comets | G34: Ub591751768536a3d75c1394b83ffa9c8 | H34: ปัญหาโปรแกรม | I34: PDF | J34: ตั้งค่าโปรแกรม | L34: Pim Patcharapan | M34: https://profile.line-scdn.net/0hySBEIswKJnxvPDb7aEZYAx9sJRZMTX9uRwg5Tw45eBwHBWUvFA1sEghsf0tVDzN_Ewg8SQhuek1jL1EacWraSGgMe01TC2AvSltsmw | N34: PDF ไม่สามารถพิมพ์เป็นภาษาไทยได้ | O34: 192.168.203.74 | R34: ดำเนินการเรียบร้อย | S34: เปิด edit adobe reader | T34: requests_Images/IT2410-035.photo.042816.jpg | U34: IT02_ก๊อต | V34: ก่อนพัฒนา App
A35: 34 | B35: IT2410-034 | C35: 45574.549 | D35: 30315 | E35: {=XLOOKUP(D35,Employee!A:A,Employee!D:D)&" "&XLOOKUP(D35,Employee!A:A,Employee!E:E)} | F35: ICT | G35: U284cb996db2131536b5800d4b800c29b | H35: ปัญหาเครือข่าย และอินเทอร์เน็ต | I35: Driveshare (ไฟล์กลาง) | J35: ไดรฟ์ไฟล์กลางหาย | L35: Dow💫45 | M35: https://profile.line-scdn.net/0hYss_zqm4BlxeJhPk1a14Iy52BTZ9V19OJUQaP2olD2thRkJdJkYdPml1DT9hEEAJd0BPOT4kX2lSNXE6QHD6aFkWW21iEUAPe0FMuw | N35: ข้อมูลในไฟล์กลางหาย หลังเน็ตหลุดทุกครั้้ง | O35: 192.168.103.59 | Q35: https://drive.google.com/file/d/10DbNU-IE98SMrsB56xpGetcEp2HubBBy/view?usp=drivesdk | R35: ดำเนินการเรียบร้อย | S35: ยกเลิก Map Drive เดิม และทำ Map Drive ใหม่ | U35: IT03_วี | V35: ก่อนพัฒนา App
A36: 35 | B36: IT2410-035 | C36: 45574.558 | D36: 11125 | E36: {=XLOOKUP(D36,Employee!A:A,Employee!D:D)&" "&XLOOKUP(D36,Employee!A:A,Employee!E:E)} | F36: Comets | G36: U898ef64932b1971d3c511d24772b7760 | H36: ปริ้นเตอร์ | I36: Printer 1 | J36: ปริ้นไม่ออก | L36: เพชร | M36: https://profile.line-scdn.net/0h6qxujkzLaV5VDHlKmMIXISVcajR2fTBMeD8nOmZYM2s_b34JcTkkOjIOMWxrOygPf2J2bWYLYDxZHx44S1qValI8NG9pOy8NcGsjuQ | N36: เครื่องปริ้นใช้ไม่ได้ค่ะ | O36: 192.168.203.68 | R36: ดำเนินการเรียบร้อย | S36: Set account printer ใช้งาน | T36: requests_Images/IT2410-037.photo.064013.png | U36: IT02_ก๊อต | V36: ก่อนพัฒนา App
A37: 36 | B37: IT2410-036 | C37: 45574.561 | D37: 31038 | E37: {=XLOOKUP(D37,Employee!A:A,Employee!D:D)&" "&XLOOKUP(D37,Employee!A:A,Employee!E:E)} | F37: ICT | G37: U7f1aca7d27b3ac8b9a77482617b703a0 | H37: ปัญหาโปรแกรม | I37: ติดตั้งโปรแกรม | J37: ระบุโปรแกรม | K37: โปรแกรม GX Works | L37: Shinnies | M37: https://profile.line-scdn.net/0h946I1eq3ZhsbMHQ8lPQYZGtgZXE4QT8JPwUgens1MS0hA3VNZ1QrKSkyb3kiByYePlUteC1nbXgXIxF9BWaaLxwAOyonByBIPlcs_A | N37: ติดตั้งโปรแกรม GX Works บนโนีตบุ๊คบริษัท | O37: 192.168.103.6 | R37: ดำเนินการเรียบร้อย | S37: ดำเนินการติดตั้งโปรแกรม GX Works | U37: IT03_วี | V37: ก่อนพัฒนา App
A38: 37 | B38: IT2410-037 | C38: 45574.607 | D38: 31043 | E38: {=XLOOKUP(D38,Employee!A:A,Employee!D:D)&" "&XLOOKUP(D38,Employee!A:A,Employee!E:E)} | F38: ICT | G38: Ueb33c059803cab01248e22ac9c846d8e | H38: คอมพิวเตอร์ | I38: Notebook | J38: ล็อคอินไม่ได้ | L38: JOEY | M38: https://profile.line-scdn.net/0h3OUNMdD5bGB4N3zHDKUSHwhnbwpbRjVyVFQiU0xnZ1YWUH82VgZzUUtgZQBHAyJkXVBxBR1gMVl0JBsGZmGQVH8HMVFEACozXVAmhw | N38: เนื่องจากไม่สามารถเข้าใช้งาน notebook ได้ เพราะรหัสเข้าใช้งานหมดอายุครับ รบกวน IT ดำเนินการแก้ไขให้หน่อยครับ ขอบคุณครับ | R38: ดำเนินการเรียบร้อย | S38: แนะนำการตั้งรหัสใหม่ให้ User สามารถตั้งรหัสเองได้เลย | U38: IT03_วี | V38: ก่อนพัฒนา App
A39: 38 | B39: IT2410-038 | C39: 45574.626 | F39: Comets | G39: Ub591751768536a3d75c1394b83ffa9c8 | H39: ขอสิทธิ์เข้าระบบ (ทำใบขอสิทธิ์) | I39: พนักงานใหม่ | J39: เซ็ทอัพคอมพิวเตอร์ | L39: Pim Patcharapan | M39: https://profile.line-scdn.net/0hySBEIswKJnxvPDb7aEZYAx9sJRZMTX9uRwg5Tw45eBwHBWUvFA1sEghsf0tVDzN_Ewg8SQhuek1jL1EacWraSGgMe01TC2AvSltsmw | N39: Set เครื่องพนักงานใหม่ | Q39: https://drive.google.com/file/d/1FG1MeNCQ1vyuAHabl96WdzLEVWu-pi8g/view?usp=drivesdk | R39: ดำเนินการเรียบร้อย | S39: Set เครื่องพนักงานใหม่เสร็จเรียบร้อย รอส่งมอบวันที่ 15/10/24 | U39: IT02_ก๊อต | V39: ก่อนพัฒนา App
A40: 39 | B40: IT2410-039 | C40: 45574.659 | D40: 31110 | E40: {=XLOOKUP(D40,Employee!A:A,Employee!D:D)&" "&XLOOKUP(D40,Employee!A:A,Employee!E:E)} | F40: ICT | G40: U0ff020f5a20fc80819822365855a34ae | H40: ขอสิทธิ์เข้าระบบ (ทำใบขอสิทธิ์) | I40: เปลี่ยนแปลงสิทธิ์ (Driveshare) | J40: ขอเพิ่มสิทธิ์ไฟล์กลาง | L40: Kookkai | M40: https://profile.line-scdn.net/0hasdY5MuLPlxJIC2UgvBAIzlwPTZqUWdOMBUhPngoY2ghE3wLY0N5PywjYTkgRXsOYxMlPn8mNW1FM0k6V3bCaE4QY211F3gPbEd0uw | N40: ขอสิทธิ์เข้าไดร์ฟ Purchase | O40: 192.168.102.197 | Q40: https://drive.google.com/file/d/17F9eou9sC4kOHVf6uha2gHvCIt1Rx4b_/view?usp=drivesdk | R40: ดำเนินการเรียบร้อย | S40: เพิ่มไดร์ฟกลาง Purchase (Read only) | U40: IT03_วี | V40: ก่อนพัฒนา App
A41: 40 | B41: IT2410-040 | C41: 45574.801 | D41: 31035 | E41: {=XLOOKUP(D41,Employee!A:A,Employee!D:D)&" "&XLOOKUP(D41,Employee!A:A,Employee!E:E)} | F41: ICT | G41: Ua090c746c823f91f76e84874b87edf92 | H41: ปัญหาโปรแกรม | I41: Email | J41: ไม่สามารถรับ / ส่งอีเมลได้ | L41: !✨BOMBAM✨🍒 | M41: https://profile.line-scdn.net/0h3IEDkce5bGZoPXxk29ESGRhtbwxLTDV0EQgqUwg6O1MGWC8yFlMlAFU0MFRUWiMyQwwnAwk9ZQZkLhsAdmuQUm8NMVdUCio1TVomgQ | N41: เมลมีปัญหา ส่งออกไม่ได้ เมลไม่เข้า | O41: 10.212.134.101,192.168.1.108 | Q41: https://drive.google.com/file/d/1mq5iluQsZ5fqTL-p3WY1hrEIF-O7YrLQ/view?usp=drivesdk | R41: ดำเนินการเรียบร้อย | S41: แบลคอัพเมล, ตั้งค่า อีเมลใหม่ | U41: IT03_วี | V41: ก่อนพัฒนา App
A42: 41 | B42: IT2410-041 | C42: 45575.393 | D42: 31038 | E42: {=XLOOKUP(D42,Employee!A:A,Employee!D:D)&" "&XLOOKUP(D42,Employee!A:A,Employee!E:E)} | F42: ICT | G42: U7f1aca7d27b3ac8b9a77482617b703a0 | H42: ปัญหาโปรแกรม | I42: Email | J42: ไม่สามารถรับ / ส่งอีเมลได้ | L42: Shinnies | M42: https://profile.line-scdn.net/0h946I1eq3ZhsbMHQ8lPQYZGtgZXE4QT8JPwUgens1MS0hA3VNZ1QrKSkyb3kiByYePlUteC1nbXgXIxF9BWaaLxwAOyonByBIPlcs_A | N42: mail ENG02@ictcos.com ข้อความไม่อัพเดท ไม่ได้รับเมลล์ที่ผู้อื่นส่งมา | O42: 192.168.103.156 | R42: ดำเนินการเรียบร้อย | S42: ตั้งค่าและใส่รหัสใหม่ | U42: IT03_วี | V42: ก่อนพัฒนา App
A43: 42 | B43: IT2410-042 | C43: 45575.456 | G43: Ub2984c0b69f230dc53186e038ec4c4be | H43: ขอสิทธิ์เข้าระบบ (ทำใบขอสิทธิ์) | I43: เปลี่ยนแปลงสิทธิ์ (Driveshare) | J43: ขอเพิ่มสิทธิ์ไฟล์กลาง | L43: Maprang7️⃣8️⃣9️⃣♾️💰 | M43: https://profile.line-scdn.net/0h-WhuJ1rtcnhFDGJjVckMBzVccRJmfStqbW01GSALLk9wOjArbW1uGSIJLUF4bjcqOWtqGXBeK09JHwUeW1qOTEI8L0l5OzQrYGs4nw | N43: add Drive G and pin map in PC | O43: 203.148 | R43: ดำเนินการเรียบร้อย | S43: เพิ่มช่องทางการเข้า google drive | U43: IT01_ดุ่ย | V43: ก่อนพัฒนา App
A44: 43 | B44: IT2410-043 | C44: 45575.459 | D44: 10841 | E44: {=XLOOKUP(D44,Employee!A:A,Employee!D:D)&" "&XLOOKUP(D44,Employee!A:A,Employee!E:E)} | F44: Comets | G44: Uf4524b611f8bc68ab73dcbd658e07905 | H44: ปัญหาโปรแกรม | I44: Email | J44: อีเมลเต็ม (แบ็คอัพอีเมล) | L44: -nattamon. | M44: https://profile.line-scdn.net/0hWGBgG23NCGhvHhh2H5l2Fx9OCwJMb1F6RHETBwpNVV8HLEs2FHxPDw0aU1BWfko8RnFAWw0cBFpjDX8OcUj0XGguVVlTKU47SnlCjw | N44: เมลเต็มค่ะ (PD02) | O44: 132 | R44: ดำเนินการเรียบร้อย | S44: BackupMail pd02@comets จำนวน 4 เครื่อง ip vnc 192.168.112.83, 192.168.112.81, 192.168.112.93, 192.168.112.132 | T44: requests_Images/IT2410-045.photo.033109.jpg | U44: IT02_ก๊อต | V44: ก่อนพัฒนา App
A45: 44 | B45: IT2410-044 | C45: 45575.483 | G45: b93accac | H45: ขอสิทธิ์เข้าระบบ (ทำใบขอสิทธิ์) | I45: พนักงานใหม่ | J45: เซ็ทอัพคอมพิวเตอร์ | N45: Set เครื่องพนักงานใหม่ | R45: ดำเนินการเรียบร้อย | S45: Set เครื่องพนักงานใหม่ ตำแหน่ง HR รอส่งมอบวันที่ 15/10/24 | T45: requests_Images/IT2410-046.photo.032754.jpg | U45: IT02_ก๊อต | V45: ก่อนพัฒนา App
A46: 45 | B46: IT2410-045 | C46: 45575.491 | D46: 30658 | E46: {=XLOOKUP(D46,Employee!A:A,Employee!D:D)&" "&XLOOKUP(D46,Employee!A:A,Employee!E:E)} | F46: ICT | G46: Ufd06f7a2eb98784569f09548f82b1423 | H46: ปัญหาเครือข่าย และอินเทอร์เน็ต | I46: Driveshare (ไฟล์กลาง) | J46: เข้าไฟล์กลางไม่ได้ | L46: tum | M46: https://profile.line-scdn.net/0hFsSYohEhGVx-IA0sRzdnIw5wGjZdUUBOV08EMhhzEmQUFlleVhEFbx8iTmUWFQtdW0YCbksmQm9yM246YHblaHkQRG1CF18PW0dTuw | N46: เข้าไฟล์กลางแล้วข้อมูลหาย | O46: 192.168.103.220 | R46: ดำเนินการเรียบร้อย | S46: Disconnect และ Map Drive ใหม่ | U46: IT03_วี | V46: ก่อนพัฒนา App
A47: 46 | B47: IT2410-046 | C47: 45575.497 | D47: 11122 | E47: {=XLOOKUP(D47,Employee!A:A,Employee!D:D)&" "&XLOOKUP(D47,Employee!A:A,Employee!E:E)} | F47: Comets | G47: Ub2984c0b69f230dc53186e038ec4c4be | H47: ปัญหาโปรแกรม | I47: โปรแกรมอื่นๆ (โปรดระบุ) | J47: โปรดระบุ | L47: Maprang7️⃣8️⃣9️⃣♾️💰 | M47: https://profile.line-scdn.net/0h-WhuJ1rtcnhFDGJjVckMBzVccRJmfStqbW01GSALLk9wOjArbW1uGSIJLUF4bjcqOWtqGXBeK09JHwUeW1qOTEI8L0l5OzQrYGs4nw | N47: set default ให้เปิดไฟล์ใน SAP ผ่าน ADOBE | O47: 203.148 | R47: ดำเนินการเรียบร้อย | S47: เพิ่มส่วนขยาย PDF | T47: requests_Images/IT2410-048.photo.063421.png | U47: IT02_ก๊อต | V47: ก่อนพัฒนา App
A48: 47 | B48: IT2410-047 | C48: 45575.544 | D48: 11125 | E48: {=XLOOKUP(D48,Employee!A:A,Employee!D:D)&" "&XLOOKUP(D48,Employee!A:A,Employee!E:E)} | F48: Comets | G48: U07f9748ea570cf71d12fb58965e96f70 | H48: ปัญหาโปรแกรม | I48: Email | J48: อื่นๆ (โปรดระบุ) | K48: แก้ไขชื่อเล่นใน Email | L48: Parichat | M48: https://profile.line-scdn.net/0hQ6H6eGtrDhllTx69FftwZhUfDXNGPlcLQC4RL1gaUX4PeBscTXsUfwAYAi1Zek8cSCFCfVVPVilpXHl_exnyLWJ_UyhZeEhKQChE_g | N48: รบกวนแก้ไขชื่อเมลล์ ชื่อเล่นในวงเล็บ จาก Pum เป็น Bum ค่ะ | O48: 192.168.203.68 | Q48: https://drive.google.com/file/d/1On8ja7DlloF7Wrxg8gQJmbK-YI37rH6m/view?usp=drivesdk | R48: ดำเนินการเรียบร้อย | S48: Edite your name outlook Pum เป็น Bum | T48: requests_Images/IT2410-049.photo.061934.png | U48: IT02_ก๊อต | V48: ก่อนพัฒนา App
A49: 48 | B49: IT2410-048 | C49: 45575.604 | D49: 11097 | E49: {=XLOOKUP(D49,Employee!A:A,Employee!D:D)&" "&XLOOKUP(D49,Employee!A:A,Employee!E:E)} | F49: Comets | G49: U6b41b082feda14eb1f1374f7f93a24bf | H49: ขอสิทธิ์เข้าระบบ (ทำใบขอสิทธิ์) | I49: เปลี่ยนแปลงสิทธิ์ (คอมพิวเตอร์) | J49: ขอยืมคอมพิวเตอร์ | L49: Gamnoi 📍 | M49: https://profile.line-scdn.net/0h6QFDJGtsaX5rPXqJu-wXARttahRITDBsRlsmHF85YBkBDHwpEw52T1Y0MhlTCXstQl51HQ5tN0hnLh4YdWuVSmwNNE9XCi8tTlojmQ | N49: ทางHR ขอยืมNotebook เพื่อปฐมนิเทศในวันอังคาร ที่ 15 ตุลาคม 2567 ค่ะ | R49: ดำเนินการเรียบร้อย | S49: Set Notebook ปฐมนิเทศ | U49: IT02_ก๊อต | V49: ก่อนพัฒนา App
A50: 49 | B50: IT2410-049 | C50: 45575.624 | D50: 11107 | E50: {=XLOOKUP(D50,Employee!A:A,Employee!D:D)&" "&XLOOKUP(D50,Employee!A:A,Employee!E:E)} | F50: Comets | G50: Ub591751768536a3d75c1394b83ffa9c8 | H50: ปัญหาโปรแกรม | I50: PDF | J50: ตั้งค่าโปรแกรม | L50: Pim Patcharapan | M50: https://profile.line-scdn.net/0hySBEIswKJnxvPDb7aEZYAx9sJRZMTX9uRwg5Tw45eBwHBWUvFA1sEghsf0tVDzN_Ewg8SQhuek1jL1EacWraSGgMe01TC2AvSltsmw | N50: PDF ขึ้นข้อความPopup ให้คลิ๊กออกจากPDF ตลอดเวลา | O50: 192.168.203.74 | Q50: https://drive.google.com/file/d/1xEgnhKPgChjK7ZYH_nlMSLBCv5iIITpe/view?usp=drivesdk | R50: ดำเนินการเรียบร้อย | S50: Adobe CreativeCloud Cleaner Tool ลง adobe reader ใหม่ | U50: IT02_ก๊อต | V50: ก่อนพัฒนา App
A51: 50 | B51: IT2410-050 | C51: 45575.636 | D51: 11083 | E51: {=XLOOKUP(D51,Employee!A:A,Employee!D:D)&" "&XLOOKUP(D51,Employee!A:A,Employee!E:E)} | F51: Comets | G51: Ua9dd326aec05e66d819e8d770cbf17da | H51: ปัญหาโปรแกรม | I51: Email | J51: อีเมลเต็ม (แบ็คอัพอีเมล) | L51: Sam | M51: https://profile.line-scdn.net/0huXc8Ab8bKndOQTqD2StUCD4RKR1tMHNlMiZhQilAfEAgd2kjYncyES9AdkMhdz4gNnVgEC4VchNCUl0RUBfWQ0lxd0ZydmwkayZgkA | N51: Outlook Backup mail เต็มไม่สามารถย้ายจดหมาย Inbox มาเก็บได้ครับ | O51: 192.168.203.141 | Q51: https://drive.google.com/file/d/1US8LYWqFFYdFK1bwKPJ3OgxaMNRo844k/view?usp=drivesdk | R51: ดำเนินการเรียบร้อย | S51: ใช้งานโปรแกรม Unlimit_PSTsize outlook | U51: IT02_ก๊อต | V51: ก่อนพัฒนา App
A52: 51 | B52: IT2410-051 | C52: 45575.697 | D52: 30315 | E52: {=XLOOKUP(D52,Employee!A:A,Employee!D:D)&" "&XLOOKUP(D52,Employee!A:A,Employee!E:E)} | F52: ICT | G52: U284cb996db2131536b5800d4b800c29b | H52: ปัญหาโปรแกรม | I52: ติดตั้งโปรแกรม | J52: โปรแกรม Express | L52: Dow💫45 | M52: https://profile.line-scdn.net/0hYss_zqm4BlxeJhPk1a14Iy52BTZ9V19OJUQaP2olD2thRkJdJkYdPml1DT9hEEAJd0BPOT4kX2lSNXE6QHD6aFkWW21iEUAPe0FMuw | N52: ลงโปรแกรมexpress | O52: 192.168.103.59 | R52: ดำเนินการเรียบร้อย | S52: ทำ Shortcut โปรแกรม Express, ประสานพี่นุชสร้าง Username, Pasword | U52: IT03_วี | V52: ก่อนพัฒนา App
A53: 52 | B53: IT2410-052 | C53: 45576.33 | F53: ICT | G53: U284cb996db2131536b5800d4b800c29b | H53: ปัญหาเครือข่าย และอินเทอร์เน็ต | I53: Driveshare (ไฟล์กลาง) | J53: เข้าไฟล์กลางไม่ได้ | L53: Dow💫45 | M53: https://profile.line-scdn.net/0hYss_zqm4BlxeJhPk1a14Iy52BTZ9V19OJUQaP2olD2thRkJdJkYdPml1DT9hEEAJd0BPOT4kX2lSNXE6QHD6aFkWW21iEUAPe0FMuw | N53: เข้าไฟล์กลางแล้วข้อมูลหาย ลองเปิด-ปิดwifi เหมือนเดิม แล้วrefresh ก็ยังไม่หายค่ะ | O53: 192.168.103.59 | R53: ดำเนินการเรียบร้อย | S53: ตั้งค่า username ในการเข้าไดร์ฟกลาง, และ Mapdrive ใหม่ | U53: IT03_วี | V53: ก่อนพัฒนา App
A54: 53 | B54: IT2410-053 | C54: 45576.361 | D54: 10594 | E54: {=XLOOKUP(D54,Employee!A:A,Employee!D:D)&" "&XLOOKUP(D54,Employee!A:A,Employee!E:E)} | F54: Comets | G54: U531c51794d7fcb3d37d6e65612cbcd50 | H54: ปัญหาเครือข่าย และอินเทอร์เน็ต | I54: อินเทอร์เน็ต | J54: เชื่อม WiFi ไม่ได้ | L54: P | M54: https://profile.line-scdn.net/0hnb6r03nDMU0bCyRx8j9PMmtbMic4emhfN2V5f3kPai0iPiFJNGl5fy0MO3ghaCRMY2kqeCoKZy0XGEYrBV3NeRw7bHwnPHcePmx7qg | N54: Note book WiFi ต่อไม่ได้ครับ | Q54: https://drive.google.com/file/d/155QkuUINekfTJNdIjD8K9HQEezt3BFAJ/view?usp=drivesdk | R54: ดำเนินการเรียบร้อย | S54: User แก้ไขปัญหาด้วย ตัวเองโดยการ reboot notebook สามารถใช้งานได้ปกติ | U54: IT02_ก๊อต | V54: ก่อนพัฒนา App
A55: 54 | B55: IT2410-054 | C55: 45576.368 | D55: 10375 | E55: {=XLOOKUP(D55,Employee!A:A,Employee!D:D)&" "&XLOOKUP(D55,Employee!A:A,Employee!E:E)} | F55: บริษัทอื่นๆในเครือ | G55: U882882471239cc5b23232e56c0ddbc99 | H55: คอมพิวเตอร์ | I55: Notebook | J55: หน้าจอฟ้า | L55: Birth | M55: https://profile.line-scdn.net/0hfqxQaeG2OV5VKBL0DDxHISV4OjR2WWBMLk8hbTR6YjptSn1YcBt3azMtZ2ttGXlccBtxOGl_ZWlZO044S37FalIYZG9pH38NcE9zuQ | N55: คอมขึ้นจอฟ้า (ตามภาพ) | O55: - | Q55: https://drive.google.com/file/d/1Cg_CgmR81YeXMpvmZpDslQpB8X1lvtsy/view?usp=drivesdk | R55: ดำเนินการเรียบร้อย | S55: sfc /scannow แก้ไขปัญหาไฟล์ระบบที่เสียหาย, update graphic intel | U55: IT02_ก๊อต | V55: ก่อนพัฒนา App
A56: 55 | B56: IT2410-055 | C56: 45576.421 | D56: 90216 | E56: {=XLOOKUP(D56,Employee!A:A,Employee!D:D)&" "&XLOOKUP(D56,Employee!A:A,Employee!E:E)} | F56: Comets | G56: U898ef64932b1971d3c511d24772b7760 | H56: ปัญหาโปรแกรม | I56: Email | J56: อีเมลเต็ม (แบ็คอัพอีเมล) | L56: เพชร | M56: https://profile.line-scdn.net/0h6qxujkzLaV5VDHlKmMIXISVcajR2fTBMeD8nOmZYM2s_b34JcTkkOjIOMWxrOygPf2J2bWYLYDxZHx44S1qValI8NG9pOy8NcGsjuQ | N56: แบล็คอัพเมล pcm 32หน่อยค่ะ | O56: 192.168.202.237 | R56: ดำเนินการเรียบร้อย | S56: Add BackupMail_pcm32 drive D | T56: requests_Images/IT2410-057.photo.031532.jpg | U56: IT02_ก๊อต | V56: ก่อนพัฒนา App
A57: 56 | B57: IT2410-056 | C57: 45576.423 | D57: 10074 | E57: {=XLOOKUP(D57,Employee!A:A,Employee!D:D)&" "&XLOOKUP(D57,Employee!A:A,Employee!E:E)} | F57: Comets | G57: U003cbc2bd203e04ac84f2c28cbcf9256 | H57: ขอสิทธิ์เข้าระบบ (ทำใบขอสิทธิ์) | I57: เปลี่ยนแปลงสิทธิ์ (ปริ้นเตอร์) | J57: ขอเพิ่มสิทธิ์ปริ้นเตอร์ (ขาว-ดำ) | L57: N'Aor | M57: https://profile.line-scdn.net/0h7lR9eok9aEN_QHqC71EWPA8QaylcMTFRVyclJ09EM3EWcigRBC8mJ0tJMyZBJ3tFAHYuIE9JMidzUx8lYRaUd3hwNXJDdy4QWicipA | N57: ขอเพิ่มสิทธ์ปริ้นจำนวน 500 แผ่นจาก1,000 แผ่น เนื่องจากปริ้นบิล CM+JA ที่เครื่องปริ้นฝั่ง FAC | O57: 192.168.203.175 | Q57: https://drive.google.com/file/d/1XyLF5eytOE424mACsH6k7Up4khF12Zt7/view?usp=drivesdk | R57: ดำเนินการเรียบร้อย | S57: เพิ่มสิทธิ์ print 500 แผ่น ตามใบขอสิทธิ์ใช้งาน | U57: IT02_ก๊อต | V57: ก่อนพัฒนา App
A58: 57 | B58: IT2410-057 | C58: 45576.429 | D58: 11124 | E58: {=XLOOKUP(D58,Employee!A:A,Employee!D:D)&" "&XLOOKUP(D58,Employee!A:A,Employee!E:E)} | F58: Comets | G58: Udcf2d1a19ecd7eb3dc9c1bf3b133a417 | H58: ขอสิทธิ์เข้าระบบ (ทำใบขอสิทธิ์) | I58: เปลี่ยนแปลงสิทธิ์ (Driveshare) | J58: ขอเพิ่มสิทธิ์ไฟล์กลาง | L58: Air...♐ ...แอร์... | M58: https://profile.line-scdn.net/0h4WU97CJia3h4QHvpOGoVBwgQaBJbMTJqAy5wH0RGZx0XcHwnUyN2Hh5CYEtBJyh-B3UsGUkUNx90UxweZhaXTH9wNklEdy0rXSchnw | N58: ขอเพิ่ม Share Drive SCM ICT เพื่อเข้าไปกรอกข้อมูลเก็บงาน | O58: 192.168.203.139 | Q58: https://drive.google.com/file/d/1mx03Ev3TnA9ATdD9glMhX6YzoZZAoO2F/view?usp=drivesdk | R58: ดำเนินการเรียบร้อย | S58: Map Drive SCM ICT ตามใบขอสิทธิ์การใช้งาน | T58: requests_Images/IT2410-059.photo.035055.jpg | U58: IT02_ก๊อต | V58: ก่อนพัฒนา App
A59: 58 | B59: IT2410-058 | C59: 45576.459 | D59: 31034 | E59: {=XLOOKUP(D59,Employee!A:A,Employee!D:D)&" "&XLOOKUP(D59,Employee!A:A,Employee!E:E)} | G59: U3d814c8b2cc2b94446ad3ff17db929bf | H59: ปัญหาโปรแกรม | I59: โปรแกรมอื่นๆ (โปรดระบุ) | J59: โปรดระบุ | L59: ANIA | M59: https://profile.line-scdn.net/0ha4Tcp3p0Pht5Gi65A0ZAZAlKPXFaa2cJAXl4dEpOYChEfntIBXt0fEtJMyNHKisZAH0hL0hPNH91CUl9Z0zCL34qYypFLXhIXH10_A | N59: เปิดไลน์ไม่ได้ค้าาาาา | O59: 192.168.103.250 | Q59: https://drive.google.com/file/d/123lBEvhKqce0z7MvMpLU03qGMdXMmAsK/view?usp=drivesdk | R59: ดำเนินการเรียบร้อย | S59: ให้ใช้ไลน์จาก chrome รอ Reset คอมวันอังคาร | U59: IT03_วี | V59: ก่อนพัฒนา App
A60: 59 | B60: IT2410-059 | C60: 45576.475 | D60: 30398 | E60: ธัญญรัตน์ หิรัญวงษ์ | F60: ICT | G60: U9e19abc838c7c00bd4995b0f827245bd | H60: ปัญหาเครือข่าย และอินเทอร์เน็ต | I60: Driveshare (ไฟล์กลาง) | J60: เข้าไฟล์กลางไม่ได้ | L60: WaWa 와와 🍀🐰🐻 | M60: https://profile.line-scdn.net/0hpt5JLRQTL1sYMz3IrD1RJGhjLDE7QnZJNFVnbXo0IWogUWkIPVQybysyIWkkBGwPM1dgaiU7eG4UIFg9BmXTbx8DcmokBGkIPVRlvA | N60: Sever เข้าไม่ได้ค่ะ ไม่ทราบว่าเกิดปัญหาอะไรมั้ยคะ คอมพื้นที่ส่วนงาน rd เป็นทุกเครื่องค่ะ | Q60: https://drive.google.com/file/d/1vOFc8O4rByMiYFIstfiULLEkj5ADfjqe/view?usp=drivesdk | R60: ดำเนินการเรียบร้อย | S60: ไอทีดำเนินการ reboot ระบบ | U60: IT03_วี | V60: ก่อนพัฒนา App
A61: 60 | B61: IT2410-060 | C61: 45576.495 | D61: 10937 | E61: {=XLOOKUP(D61,Employee!A:A,Employee!D:D)&" "&XLOOKUP(D61,Employee!A:A,Employee!E:E)} | F61: Comets | G61: U33b5dc295034c6b8d3b0f1ca3a491fa8 | H61: ปัญหาโปรแกรม | I61: Email | J61: ภาษาเพี้ยน | L61: Cye♾️⭐️ | M61: https://profile.line-scdn.net/0htC9SvZ6TK2wUKjnzfiBVE2R6KAY3W3J-PBw3CiB9dV8gGGkybR9sCycoJlUgTWpvO0kxWXEudVwYOVwKCnzXWBMadl0oHW0_MU1hiw | N61: เวลามีเมลล์เด้งมา แล้วตักอักษรมันจะยึกยือๆอ่านไม่ได้ค่ะ ส่งเมลล์ตอบได้บ้างไม่ได้บ้าง แต่เครื่องของต้นทางที่ส่งเมลล์มาและเมลล์อื่นที่cc ไว้ไม่เป็นค่ะ เป็นแค่ที่เครื่องของหนู | O61: 192.168.202.232 | Q61: https://drive.google.com/file/d/1reuPfvrN0WZoQ8DjxktGpeVly9ZsYVjp/view?usp=drivesdk | R61: ดำเนินการเรียบร้อย | S61: Repair office 365 | U61: IT02_ก๊อต | V61: ก่อนพัฒนา App
A62: 61 | B62: IT2410-061 | C62: 45576.497 | D62: 11122 | E62: {=XLOOKUP(D62,Employee!A:A,Employee!D:D)&" "&XLOOKUP(D62,Employee!A:A,Employee!E:E)} | F62: Comets | G62: Ub2984c0b69f230dc53186e038ec4c4be | H62: ขอสิทธิ์เข้าระบบ (ทำใบขอสิทธิ์) | I62: เปลี่ยนแปลงสิทธิ์ (Driveshare) | J62: ขอเพิ่มสิทธิ์ไฟล์กลาง | L62: Maprang7️⃣8️⃣9️⃣♾️💰 | M62: https://profile.line-scdn.net/0h-WhuJ1rtcnhFDGJjVckMBzVccRJmfStqbW01GSALLk9wOjArbW1uGSIJLUF4bjcqOWtqGXBeK09JHwUeW1qOTEI8L0l5OzQrYGs4nw | N62: รบกวน map drive admin เพิ่มให้หน่อยค่ะ | O62: 203.148 | R62: ดำเนินการเรียบร้อย | S62: กำหนด Permissions เข้าใช้งาน drive 4 PCM PCM32 ADMIN เพื่อใช้ในการทำงานของ admin (ตามใบขอสิทธิ์) | U62: IT02_ก๊อต | V62: ก่อนพัฒนา App
A63: 62 | B63: IT2410-062 | C63: 45576.553 | D63: 11109 | E63: {=XLOOKUP(D63,Employee!A:A,Employee!D:D)&" "&XLOOKUP(D63,Employee!A:A,Employee!E:E)} | F63: Comets | G63: U92b3e443ef8168abc9dc83aea500b925 | H63: ปัญหาเครือข่าย และอินเทอร์เน็ต | I63: Driveshare (ไฟล์กลาง) | J63: ขอเพิ่มสิทธิ์ไฟล์กลาง | L63: Sakanazz 896 | M63: https://profile.line-scdn.net/0hbIRvaeVWPWZ_Dy2BWENDGQ9fPgxcfmR0A2wlUE9dNFNGOHJnUTp3Uk8KYF5FPillWmsnAxoOZlVzHEoAYVnBUng_YFdDOHs1Wmh3gQ | N63: ไม่สามารถเข้าใช้งาน ไฟล์ส่วนกลางได้ครับ | O63: 192.168.202.31 | Q63: https://drive.google.com/file/d/17d_NN6ZI25JiiHq7F71hprkCF3XqJXqV/view?usp=drivesdk | R63: ดำเนินการเรียบร้อย | S63: Password หมดอายุ ทำให้ไม่สามารถใช้งาน drive share ได้ | T63: requests_Images/IT2410-064.photo.034522.jpg | U63: IT02_ก๊อต | V63: ก่อนพัฒนา App
A64: 63 | B64: IT2410-063 | C64: 45576.578 | D64: 31142 | E64: {=XLOOKUP(D64,Employee!A:A,Employee!D:D)&" "&XLOOKUP(D64,Employee!A:A,Employee!E:E)} | F64: ICT | G64: U9e8232d257a28b27c3822a1e6092bf25 | H64: ขอสิทธิ์เข้าระบบ (ทำใบขอสิทธิ์) | I64: เปลี่ยนแปลงสิทธิ์ (Driveshare) | J64: ขอเพิ่มสิทธิ์ไฟล์กลาง | L64: ณฐกร | M64: https://profile.line-scdn.net/0h-KDWyvTdcmRpLmMB_eAMGxl-cQ5KXyt2FRtuAFUoLFFcSjQ0QUo9VVosLFMDF2c1F0pqC1sqLlJlPQUCd3iOUG4eL1VVGTQ3TEk4gw | N64: เข้าไดร์ฟกลาง | O64: 192.168.203.24 | R64: ดำเนินการเรียบร้อย | S64: ตรวจสอบสามารถเข้าใช้งานได้ปกติ | T64: requests_Images/IT2410-065.photo.065919.jpg | U64: IT02_ก๊อต | V64: ก่อนพัฒนา App
A65: 64 | B65: IT2410-064 | C65: 45576.59 | D65: 10630 | E65: {=XLOOKUP(D65,Employee!A:A,Employee!D:D)&" "&XLOOKUP(D65,Employee!A:A,Employee!E:E)} | F65: Comets | G65: U119eab32108f3e09e260f57b4680ead7 | H65: ปัญหาโปรแกรม | I65: PDF | J65: ตั้งค่าโปรแกรม | L65: Finance.acc_cm | M65: https://profile.line-scdn.net/0hOQt_9TSDEH5ZJgKmI7FuASl2ExR6V0lscEFZSmohTRxjEFcvcURZSDgmHktlE1V_JklXTGggS05VNWcYR3DsSl4WTU9lEVYtfEFamQ | N65: แก้ไข้pdf | O65: 192.168.203.185 | R65: ดำเนินการเรียบร้อย | S65: เปิดไฟล์เป็น google chrome Set default adobe reader | U65: IT02_ก๊อต | V65: ก่อนพัฒนา App
A66: 65 | B66: IT2410-065 | C66: 45576.64 | D66: 11089 | E66: {=XLOOKUP(D66,Employee!A:A,Employee!D:D)&" "&XLOOKUP(D66,Employee!A:A,Employee!E:E)} | F66: Comets | G66: Ub71ccfe3bb0473f696fb48f4360798ff | H66: ปริ้นเตอร์ | I66: ปริ้นเตอร์อื่นๆ | J66: ปริ้นไม่ออก | L66: TONNAM | M66: https://profile.line-scdn.net/0hxT2XD7ZZJ3sfITYbs_RZBG9xJBE8UH5pNUM6HSoleBgiRGAlZxQ_Siwjek53QWV-OxQ7Hn8ieUkTMlAdAXfbTxgRekojFmEoOkZtnA | N66: สั่งปริ้นไม่ได้ค่ะ | O66: 192.168.203.173 | R66: ดำเนินการเรียบร้อย | S66: User ไม่มีการส่งใบขอสิทธิ์ print จึงดำเนินการปิด Ticket วันจันทร์มีการ re สิทธิ์ print ใช้งาน ถ้ากรณีจะขอเพิ่มรบกวนเขียนใบขอสิทธิ์ใช้งานส่ง Ticket มาอีกครั้ง | T66: requests_Images/IT2410-067.photo.020040.png | U66: IT02_ก๊อต | V66: ก่อนพัฒนา App
A67: 66 | B67: IT2410-066 | C67: 45576.688 | D67: 11120 | E67: {=XLOOKUP(D67,Employee!A:A,Employee!D:D)&" "&XLOOKUP(D67,Employee!A:A,Employee!E:E)} | F67: Comets | G67: U873d737245a2891135faba9e654260ee | H67: ขอสิทธิ์เข้าระบบ (ทำใบขอสิทธิ์) | I67: เปลี่ยนแปลงสิทธิ์ (ปริ๊นเตอร์) | J67: ขอเพิ่มสิทธิ์ปริ้นเตอร์ (ขาว-ดำ) | L67: 𝐍𝐎𝐎𝐍 | M67: https://profile.line-scdn.net/0hjMPvVgN0NWJ9DyV4HhFLHQ1fNghefmxwA29_UUEJa1UVbSAzUTt6VhgIYwBAO3EzAWkvA0EIaFNxHEIEY1nJVno_aFNBOHMxWGh_hQ | N67: ขอใช้สิทธิ์เครื่องปริ้นท์ | O67: 192.168.202.73 | R67: ดำเนินการเรียบร้อย | S67: Set account printer ใช้งาน | T67: requests_Images/IT2410-068.photo.093741.jpg | U67: IT02_ก๊อต | V67: ก่อนพัฒนา App
A68: 67 | B68: IT2410-067 | C68: 45576.703 | D68: 11125 | E68: {=XLOOKUP(D68,Employee!A:A,Employee!D:D)&" "&XLOOKUP(D68,Employee!A:A,Employee!E:E)} | F68: Comets | G68: U07f9748ea570cf71d12fb58965e96f70 | H68: ปัญหาโปรแกรม | I68: Email | J68: อีเมลเต็ม (แบ็คอัพอีเมล) | L68: Parichat | M68: https://profile.line-scdn.net/0hQ6H6eGtrDhllTx69FftwZhUfDXNGPlcLQC4RL1gaUX4PeBscTXsUfwAYAi1Zek8cSCFCfVVPVilpXHl_exnyLWJ_UyhZeEhKQChE_g | N68: รบกวนทำ Backup mail ให้หน่อยค่ะ เมลล์เต็ม | O68: 192.168.203.68 | R68: ดำเนินการเรียบร้อย | S68: ดำเนินการ BackupMail ด้วยตัวเอง | U68: IT02_ก๊อต | V68: ก่อนพัฒนา App
A69: 68 | B69: IT2410-068 | C69: 45579.329 | D69: 31056 | E69: {=XLOOKUP(D69,Employee!A:A,Employee!D:D)&" "&XLOOKUP(D69,Employee!A:A,Employee!E:E)} | F69: ICT | G69: U3802b6d2de6fd2929042e87a8c5268d8 | H69: ปัญหาโปรแกรม | I69: Email | J69: อีเมลเต็ม (แบ็คอัพอีเมล) | L69: Nooanny | M69: https://profile.line-scdn.net/0hV7fTPKhZCRhLLRqSgH13Zzt9CnJoXFAKYUkTeHp-Uyx0TUobYxsUensrBy8kGkxIYUpOLHgrUX9HPn5-VXv1LEwdVCl3Gk9LbkpD_w | N69: รบกวนเก็บข้อมูลใน mail ให้หน่อยครับ จะทำการลบข้อมูลใน mail เนื่องจากข้อมูลเต็มแล้วค่ะ | R69: ดำเนินการเรียบร้อย | S69: แนะนำวิธีการแบล็คอัพเมล | U69: IT03_วี | V69: ก่อนพัฒนา App
A70: 69 | B70: IT2410-069 | C70: 45579.377 | D70: 31034 | E70: {=XLOOKUP(D70,Employee!A:A,Employee!D:D)&" "&XLOOKUP(D70,Employee!A:A,Employee!E:E)} | F70: ICT | G70: U3d814c8b2cc2b94446ad3ff17db929bf | H70: ปริ้นเตอร์ | I70: ปริ้นเตอร์อื่นๆ | J70: ปริ้นไม่ออก | L70: ANIA | M70: https://profile.line-scdn.net/0ha4Tcp3p0Pht5Gi65A0ZAZAlKPXFaa2cJAXl4dEpOYChEfntIBXt0fEtJMyNHKisZAH0hL0hPNH91CUl9Z0zCL34qYypFLXhIXH10_A | N70: ปริ้นงานไม่ได้ | O70: 192.168.103.250 | Q70: https://drive.google.com/file/d/19cHgiaUn97Gldd51wNLyIuZCLNY7Z6jH/view?usp=drivesdk | R70: ดำเนินการเรียบร้อย | U70: IT03_วี | V70: ก่อนพัฒนา App
A71: 70 | B71: IT2410-070 | C71: 45580.364 | D71: 11109 | E71: {=XLOOKUP(D71,Employee!A:A,Employee!D:D)&" "&XLOOKUP(D71,Employee!A:A,Employee!E:E)} | F71: Comets | G71: U92b3e443ef8168abc9dc83aea500b925 | H71: คอมพิวเตอร์ | I71: Notebook | J71: ล็อคอินไม่ได้ | L71: Sakanazz 896 | M71: https://profile.line-scdn.net/0hbIRvaeVWPWZ_Dy2BWENDGQ9fPgxcfmR0A2wlUE9dNFNGOHJnUTp3Uk8KYF5FPillWmsnAxoOZlVzHEoAYVnBUng_YFdDOHs1Wmh3gQ | N71: ใช้รหัสใหม่เข้าเครื่องไม่ได้ | R71: ดำเนินการเรียบร้อย | S71: User แจ้งว่าเข้าใช้งานได้แล้ว | U71: IT02_ก๊อต | V71: ก่อนพัฒนา App
A72: 71 | B72: IT2410-071 | C72: 45580.372 | D72: 31017 | E72: {=XLOOKUP(D72,Employee!A:A,Employee!D:D)&" "&XLOOKUP(D72,Employee!A:A,Employee!E:E)} | F72: ICT | G72: U456fd4c9b74b26748a8a981b1d43c1cb | H72: ปัญหาโปรแกรม | I72: Microsoft Office (Word, Excel, Power Point) | J72: อื่นๆ (โปรดระบุ) | K72: ตั้งค่า Excel | L72: PIYATHIDA | M72: https://profile.line-scdn.net/0hX2PHp8LdBx19MReCtut5Yg1hBHdeQF4PUVEfeU0xC3pEA0hJWF8aeUg3WSVGVEJMUAJOfEgxXC5xInB7Y2f7KXoBWixBBkFOWFZN-g | N72: จะเปิดไฟล์นี้ในexcel แต่ไฟล์มาขึ้นในโปรแกรมนี้ค่ะ | O72: 192.168.103.212 | Q72: https://drive.google.com/file/d/1NxzD2C1WjfJFgTsvfJ-WJ6I5QVTI8jL6/view?usp=drivesdk | R72: ดำเนินการเรียบร้อย | S72: ตั้งค่า Excel | U72: IT03_วี | V72: ก่อนพัฒนา App
A73: 72 | B73: IT2410-072 | C73: 45580.379 | D73: 20021 | E73: {=XLOOKUP(D73,Employee!A:A,Employee!D:D)&" "&XLOOKUP(D73,Employee!A:A,Employee!E:E)} | F73: Comets | G73: U119eab32108f3e09e260f57b4680ead7 | H73: อุปกรณ์ไอที | I73: เครื่องสำรองไฟ | J73: เครื่องเปิดไม่ติด | L73: Finance.acc_cm | M73: https://profile.line-scdn.net/0hOQt_9TSDEH5ZJgKmI7FuASl2ExR6V0lscEFZSmohTRxjEFcvcURZSDgmHktlE1V_JklXTGggS05VNWcYR3DsSl4WTU9lEVYtfEFamQ | N73: เรียน คุณฝ่ายไฮที เครื่องสำรองไฟไม่ติด ของฝ่ายบัญชี กรุณาช่วยมาตรวจสอบให้ด้วยนะคะ ตอนนี้ยังเปิดคอมไม่ได้คะ aum คะ ขอบพระคุณเป็นอย่างสูงคะ | R73: ดำเนินการเรียบร้อย | S73: แก้ไขด้วยตนเอง
A74: 73 | B74: IT2410-073 | C74: 45580.381 | D74: 10809 | E74: {=XLOOKUP(D74,Employee!A:A,Employee!D:D)&" "&XLOOKUP(D74,Employee!A:A,Employee!E:E)} | F74: ICT | G74: U3cde6374df8e77323adcb682c7dd664d | H74: คอมพิวเตอร์ | I74: Notebook | J74: เครื่องเปิดไม่ติด | L74: Stang 💖 | M74: https://profile.line-scdn.net/0hPZATNm3iD3VsLR8bK4BxChx9DB9PXFZnEkJDR1EvWUFWG08kQBtBGlx4AUZYGx8rQ0MXRlt5WE1gPngTcnvzQWsdUkRQGkkmSUpFkg | N74: Notebook เปิดไม่ติด | O74: 192.168.203.130 | R74: ดำเนินการเรียบร้อย | S74: ไฟค้าง ทำการ รีเซ็ท แบทเตอร์รี่ | U74: IT01_ดุ่ย | V74: ก่อนพัฒนา App
A75: 74 | B75: IT2410-074 | C75: 45580.397 | D75: 11109 | E75: {=XLOOKUP(D75,Employee!A:A,Employee!D:D)&" "&XLOOKUP(D75,Employee!A:A,Employee!E:E)} | F75: Comets | G75: U92b3e443ef8168abc9dc83aea500b925 | H75: ปัญหาโปรแกรม | I75: Email | J75: อีเมลเต็ม (แบ็คอัพอีเมล) | L75: Sakanazz 896 | M75: https://profile.line-scdn.net/0hbIRvaeVWPWZ_Dy2BWENDGQ9fPgxcfmR0A2wlUE9dNFNGOHJnUTp3Uk8KYF5FPillWmsnAxoOZlVzHEoAYVnBUng_YFdDOHs1Wmh3gQ | N75: Back up อีเมลล์ มีปัญหาข้อมูลหาย | O75: 192.168.202.138 | R75: ดำเนินการเรียบร้อย | S75: outlook repair/scanpst ทดสอบ BackupMail อีกครั้ง ใช้งานได้ | U75: IT02_ก๊อต | V75: ก่อนพัฒนา App
A76: 75 | B76: IT2410-075 | C76: 45580.401 | D76: 31423 | E76: พรพจน์ ศิลาคชสาร | F76: ICT | G76: U9e8232d257a28b27c3822a1e6092bf25 | H76: ขอสิทธิ์เข้าระบบ (ทำใบขอสิทธิ์) | I76: ขอสิทธิ์เข้าระบบ (ทำใบขอสิทธิ์) | J76: เปลี่ยนแปลงสิทธิ์ (Driveshare) | L76: ณฐกร | M76: https://profile.line-scdn.net/0h-KDWhuvgcmRpLmMKV74MGxl-cQ5KXyt2FRtuAFUoLFFcSjQ0QUo9VVosLFMDF2c1F0pqC1sqLlJlPQUCd3iOUG4eL1VVGTQ3TEk4gw | N76: ขอเข้าถึง โฟลเดอร์ MKT02 & SalesADM02 (ยกขึ้นระบบใหม่) | R76: ดำเนินการเรียบร้อย | S76: Set Permissions โฟลเดอร์ MKT02 & SalesADM02 (ยกขึ้นระบบใหม่) | T76: requests_Images/IT2410-077.photo.035813.jpg | U76: IT02_ก๊อต | V76: ก่อนพัฒนา App
A77: 76 | B77: IT2410-076 | C77: 45580.411 | G77: 9cd79a30 | H77: ขอสิทธิ์เข้าระบบ (ทำใบขอสิทธิ์) | I77: พนักงานใหม่ | J77: เซ็ทอัพคอมพิวเตอร์ | N77: Set เครื่องพนักงานใหม่ | R77: ดำเนินการเรียบร้อย | S77: Set เครื่องพนักงานใหม่ เริ่มงานวันที่ 15/10/24 (ได้รับใบขอสิทธิ์ช่วงเช้าวันที่ 15/10/24) | T77: requests_Images/IT2410-078.photo.042125.jpg | U77: IT02_ก๊อต | V77: ก่อนพัฒนา App
A78: 77 | B78: IT2410-077 | C78: 45580.415 | D78: 30890 | E78: {=XLOOKUP(D78,Employee!A:A,Employee!D:D)&" "&XLOOKUP(D78,Employee!A:A,Employee!E:E)} | F78: ICT | G78: U826e25d3e2a51e66b35c1c29ff58b271 | H78: ปัญหาโปรแกรม | I78: Microsoft Office (Word, Excel, Power Point) | J78: อื่นๆ (โปรดระบุ) | K78: ตั้งค่าและติดตั้ง Microsoft Office | L78: Lalita K. | M78: https://profile.line-scdn.net/0h2v9Ad85hbVkUOH3Cpt4TJmRobjM3STRLOQonayg6NDkuCi9daF0rNigxOmEgCyoHalsranNsOjsYKxo_Cm6RbRMIMGgoDysKMV8nvg | N78: Set up microsoft office for Ict Mac. | O78: 165905947 | R78: ดำเนินการเรียบร้อย | S78: ติดดตั้งและตั้งค่าการใช้งานโปรแกรม MS Office 365 | U78: IT03_วี | V78: ก่อนพัฒนา App
A79: 78 | B79: IT2410-078 | C79: 45580.424 | D79: 20032 | E79: {=XLOOKUP(D79,Employee!A:A,Employee!D:D)&" "&XLOOKUP(D79,Employee!A:A,Employee!E:E)} | F79: JA | G79: Uad5c175c02aae142cc13cc39e7a5e76f | H79: ปัญหาโปรแกรม | I79: Email | J79: อีเมลเต็ม (แบ็คอัพอีเมล) | L79: Benz | M79: https://profile.line-scdn.net/0hu8BXJA9QKhdvITprTZtUaB9xKX1MUHMFE0U1dAogIXMHEGlBRUJgeFkoICNREGVDFBVldwl2ci5jMl1xcXfWI2gRdyZTFmxESkZg8A | N79: รบกวนสร้าง BackupMail ใน Outlook ให้เครื่องของ sale manager ให้หน่อยครับ | O79: 192.168.202.146 | R79: ดำเนินการเรียบร้อย | S79: ดำเนินการสร้าง BackupMail_sales01 | T79: requests_Images/IT2410-080.photo.041523.jpg | U79: IT02_ก๊อต | V79: ก่อนพัฒนา App
A80: 79 | B80: IT2410-079 | C80: 45580.466 | D80: 11095 | E80: {=XLOOKUP(D80,Employee!A:A,Employee!D:D)&" "&XLOOKUP(D80,Employee!A:A,Employee!E:E)} | F80: Comets | G80: U898ef64932b1971d3c511d24772b7760 | H80: ปัญหาโปรแกรม | I80: SAP | J80: อื่นๆ (โปรดระบุ) | K80: Add User | L80: เพชร | M80: https://profile.line-scdn.net/0h6qxujkzLaV5VDHlKmMIXISVcajR2fTBMeD8nOmZYM2s_b34JcTkkOjIOMWxrOygPf2J2bWYLYDxZHx44S1qValI8NG9pOy8NcGsjuQ | N80: แอด รหัสำนักงานใน sap ให่หน่อยค่ะ | O80: 192.168.202.237 | R80: ดำเนินการเรียบร้อย | S80: Add user sap คุณณิชกมล เอี่ยมจรูญ | T80: requests_Images/IT2410-081.photo.045742.jpg | U80: IT02_ก๊อต | V80: ก่อนพัฒนา App
A81: 80 | B81: IT2410-080 | C81: 45580.475 | D81: 31124 | E81: {=XLOOKUP(D81,Employee!A:A,Employee!D:D)&" "&XLOOKUP(D81,Employee!A:A,Employee!E:E)} | F81: ICT | G81: U70fbf83e7cc6a05fb51263969fc8d703 | H81: ปริ้นเตอร์ | I81: ปริ้นเตอร์อื่นๆ | J81: ปริ้นไม่ได้ | L81: Joyladaaa | M81: https://profile.line-scdn.net/0hdxdykdQcO1dJACsfzF9FKDlQOD1qcWJFZjZyOX5QMWN9NShVMDUkMCwFNmcmNytRbGJxMy8CMmVFE0wxV1bHY04wZmZ1N30EbGdxsA | N81: ปริ้นท์งานไม่ได้ | O81: 192.168.102.64 | Q81: https://drive.google.com/file/d/187dkGtu1jnt8KCOraDaChC3hSQZZX5G_/view?usp=drivesdk | R81: ดำเนินการเรียบร้อย | S81: แอดปริ้นเตอร์ใหม่ | U81: IT03_วี | V81: ก่อนพัฒนา App
A82: 81 | B82: IT2410-081 | C82: 45580.474 | D82: 10352 | E82: {=XLOOKUP(D82,Employee!A:A,Employee!D:D)&" "&XLOOKUP(D82,Employee!A:A,Employee!E:E)} | F82: Comets | G82: Ub35025349734bec29cc0f423db4b562e | H82: ปัญหาโปรแกรม | I82: Email | J82: อื่นๆ (โปรดระบุ) | L82: NAN | M82: https://profile.line-scdn.net/0hc6rVvs0oPBlfLyyICXBCZi9_P3N8XmULJkx1fmh4Y31kS31NIE92f2l7NilkGX8YJBt2eT4mMC9TPEt_QXnALVgfYShjGHpKekh2_g | N82: ขอให้ดึงข้อมูลกล้องวงจรปิดของ CM-FAC บริเวณ ที่จอดรถข้างโรงงานและกล้องบริเวณหน้าด้านหน้าโรงงานในวันที่ 9.10.2024 ตั้งแต่เวลา 01.00น.-24.00น.เนื่องจากรถจักรยานยนต์ พนักงานหายค่ะ ถ้าสงสัยรบกวนโทรกลับค่ะ | R82: ดำเนินการเรียบร้อย | S82: ไม่สามารถดำเนินการให้ได้ เนื่องจากเป็นกล้องของคุณอู๋ | U82: IT01_ดุ่ย | V82: ก่อนพัฒนา App
A83: 82 | B83: IT2410-082 | C83: 45580.48 | D83: 11125 | E83: {=XLOOKUP(D83,Employee!A:A,Employee!D:D)&" "&XLOOKUP(D83,Employee!A:A,Employee!E:E)} | F83: Comets | G83: U07f9748ea570cf71d12fb58965e96f70 | H83: ขอสิทธิ์เข้าระบบ (ทำใบขอสิทธิ์) | I83: เปลี่ยนแปลงสิทธิ์ (Driveshare) | J83: ขอเพิ่มสิทธิ์ไฟล์กลาง | L83: Parichat | M83: https://profile.line-scdn.net/0hQ6H6eGtrDhllTx69FftwZhUfDXNGPlcLQC4RL1gaUX4PeBscTXsUfwAYAi1Zek8cSCFCfVVPVilpXHl_exnyLWJ_UyhZeEhKQChE_g | N83: รบกวน mat drive G ให้หน่อยค่ะ | O83: 192.168.202.104 | R83: ดำเนินการเรียบร้อย | S83: sign in google drive G sap ใช้งานภายในแผนก | T83: requests_Images/IT2410-084.photo.064858.jpg | U83: IT02_ก๊อต | V83: ก่อนพัฒนา App
A84: 83 | B84: IT2410-083 | C84: 45580.49 | D84: 10963 | E84: {=XLOOKUP(D84,Employee!A:A,Employee!D:D)&" "&XLOOKUP(D84,Employee!A:A,Employee!E:E)} | F84: Comets | G84: U0a55afcab6a38a8d2ef1704a7b6c7654 | H84: ปัญหาเครือข่าย และอินเทอร์เน็ต | I84: Email | J84: เปิดใช้งานอีเมล | L84: lllukpaddd 🎐 | M84: https://profile.line-scdn.net/0htModHbTmK2JCHToIWkJVHTJNKAhhbHJwbXxmAH8UJgB2fm8xaS5hDCNIJVd8KTthZn1tUX8acgZODlwEXEvXVkUtdlN-Km0xZ3phhQ | N84: เข้าเมลล์ใหมา | O84: 192.168.202.159 | R84: ดำเนินการเรียบร้อย | S84: ออกจาก outlook และเปิดใช้งานใหม่ | T84: requests_Images/IT2410-085.photo.045207.jpg | U84: IT02_ก๊อต | V84: ก่อนพัฒนา App
A85: 84 | B85: IT2410-084 | C85: 45580.537 | D85: 11104 | E85: {=XLOOKUP(D85,Employee!A:A,Employee!D:D)&" "&XLOOKUP(D85,Employee!A:A,Employee!E:E)} | F85: Comets | G85: U0313f7c25ff851cd3d98646001de7c27 | H85: คอมพิวเตอร์ | I85: Notebook | J85: ล็อคอินไม่ได้ | L85: ไออุ่น🔰💰 | M85: https://profile.line-scdn.net/0h0XnxxnDrb3dDAX-gLz4RCDNRbB1gcDZlPzAiFHIBMEB7YnhxbmMkFXcBYkR_MXx1a2EjFnEFNRRPEhgRXVeTQ0QxMkZ_NikkZmYlkA | N85: เนื่องจากกดรหัสเข้าไปแล้วแล้วเหมือนเครื่องให้เปลี่ยนรหัสใหม่ค่ะ | Q85: https://drive.google.com/file/d/1t5XUYCrJtnDiS2m39UmAYzWw5ETgeGax/view?usp=drivesdk | R85: ดำเนินการเรียบร้อย | S85: Reset password user ใช้งาน | U85: IT02_ก๊อต | V85: ก่อนพัฒนา App
A86: 86 | B86: IT2410-085 | C86: 45580.547 | D86: 10809 | E86: {=XLOOKUP(D86,Employee!A:A,Employee!D:D)&" "&XLOOKUP(D86,Employee!A:A,Employee!E:E)} | F86: ICT | G86: U3cde6374df8e77323adcb682c7dd664d | H86: ปัญหาโปรแกรม | I86: Email | J86: เปิดโปรแกรมไม่ได้ | L86: Stang 💖 | M86: https://profile.line-scdn.net/0hPZATNm3iD3VsLR8bK4BxChx9DB9PXFZnEkJDR1EvWUFWG08kQBtBGlx4AUZYGx8rQ0MXRlt5WE1gPngTcnvzQWsdUkRQGkkmSUpFkg | N86: เปิด outlook ไม่ได้ | O86: 192.168.203.130 | Q86: https://drive.google.com/file/d/16NrsZXTqcw0y1RUXFN8Gdh5Vco15T1hv/view?usp=drivesdk | R86: ดำเนินการเรียบร้อย | S86: End task โปรแกรม outlook เปิด outlook ใหม่อีกครั้ง | T86: requests_Images/IT2410-087.photo.034156.jpg | U86: IT02_ก๊อต | V86: ก่อนพัฒนา App
A87: 87 | B87: IT2410-086 | C87: 45580.555 | D87: 31142 | E87: {=XLOOKUP(D87,Employee!A:A,Employee!D:D)&" "&XLOOKUP(D87,Employee!A:A,Employee!E:E)} | F87: ICT | G87: U9e8232d257a28b27c3822a1e6092bf25 | H87: ขอสิทธิ์เข้าระบบ (ทำใบขอสิทธิ์) | I87: เปลี่ยนแปลงสิทธิ์ (ปริ๊นเตอร์) | J87: ขอเพิ่มสิทธิ์ปริ้นเตอร์ (ขาว-ดำ) | L87: ณฐกร | M87: https://profile.line-scdn.net/0h-KDWhuvgcmRpLmMKV74MGxl-cQ5KXyt2FRtuAFUoLFFcSjQ0QUo9VVosLFMDF2c1F0pqC1sqLlJlPQUCd3iOUG4eL1VVGTQ3TEk4gw | N87: ขอสิทธิการใช้งานเครื่องถ่ายเอกสาร | O87: 192.168.203.24 | R87: ดำเนินการเรียบร้อย | S87: Set printer ใช้งาน | T87: requests_Images/IT2410-088.photo.064948.jpg | U87: IT02_ก๊อต | V87: ก่อนพัฒนา App
A88: 88 | B88: IT2410-087 | C88: 45580.578 | D88: 11126 | E88: {=XLOOKUP(D88,Employee!A:A,Employee!D:D)&" "&XLOOKUP(D88,Employee!A:A,Employee!E:E)} | F88: Comets | G88: U826d36acb7d187642638587caf345a97 | H88: ปัญหาโปรแกรม | I88: ติดตั้งโปรแกรม | J88: อื่นๆ (โปรดระบุ) | K88: Adobe Illustrator | L88: 🌜B.Ratchada.D🌛 | M88: https://profile.line-scdn.net/0hx1oTBROKJx5CLTZxse9ZYTJ9JHRhXH4MbRg4eXB4cX57H2lBaBhvfSAofygoHWgbO0w7KiN-eXtOPlB4XHvbKkUdei9-GmFNZ0pt-Q | N88: ลงแอพ adobe ai | R88: ดำเนินการเรียบร้อย | S88: adobe creative cloud ไม่สามารถ download ได้ Our apologies. If the URL is correct and refreshing the page doesn't fix the problem, please try again later ติดตั้งเครื่องฝน MKT ใช้งานแทน | U88: IT02_ก๊อต | V88: ก่อนพัฒนา App
A89: 89 | B89: IT2410-088 | C89: 45580.603 | F89: Comets | G89: U898ef64932b1971d3c511d24772b7760 | H89: ปริ้นเตอร์ | I89: Printer สติ๊กเกอร์ | J89: ปริ้นไม่ออก | L89: เพชร | M89: https://profile.line-scdn.net/0h6qxujkzLaV5VDHlKmMIXISVcajR2fTBMeD8nOmZYM2s_b34JcTkkOjIOMWxrOygPf2J2bWYLYDxZHx44S1qValI8NG9pOy8NcGsjuQ | N89: เครื่องปริ้นสติ๊กเกอร์หมุนๆๆ ค้างๆ กดปริ้นไม่ได้ | O89: 192.168.202.237 | R89: ดำเนินการเรียบร้อย | S89: Disk Cleanup, ลบ %temp%, และนำ RAM เพิ่มการใช้งาน | U89: IT02_ก๊อต | V89: ก่อนพัฒนา App
A90: 90 | B90: IT2410-089 | C90: 45580.654 | D90: 30890 | E90: {=XLOOKUP(D90,Employee!A:A,Employee!D:D)&" "&XLOOKUP(D90,Employee!A:A,Employee!E:E)} | F90: ICT | G90: U826e25d3e2a51e66b35c1c29ff58b271 | H90: ขอสิทธิ์เข้าระบบ (ทำใบขอสิทธิ์) | I90: เปลี่ยนแปลงสิทธิ์ (Driveshare) | J90: ขอเพิ่มสิทธิ์ไฟล์กลาง | L90: Lalita K. | M90: https://profile.line-scdn.net/0h2v9Ad85hbVkUOH3Cpt4TJmRobjM3STRLOQonayg6NDkuCi9daF0rNigxOmEgCyoHalsranNsOjsYKxo_Cm6RbRMIMGgoDysKMV8nvg | N90: ขอเข้าใช้สิทธิ์ MKT department | O90: 165905947 | R90: ดำเนินการเรียบร้อย | S90: เพิ่มไดร์ฟ | U90: IT02_ก๊อต | V90: ก่อนพัฒนา App
A91: 92 | B91: IT2410-090 | C91: 45580.682 | D91: 11120 | E91: {=XLOOKUP(D91,Employee!A:A,Employee!D:D)&" "&XLOOKUP(D91,Employee!A:A,Employee!E:E)} | F91: Comets | G91: U873d737245a2891135faba9e654260ee | H91: ปัญหาเครือข่าย และอินเทอร์เน็ต | I91: อินเทอร์เน็ต | J91: ขอเชื่อมต่อ WiFi | L91: 𝐍𝐎𝐎𝐍 | M91: https://profile.line-scdn.net/0hjMPvVgN0NWJ9DyV4HhFLHQ1fNghefmxwA29_UUEJa1UVbSAzUTt6VhgIYwBAO3EzAWkvA0EIaFNxHEIEY1nJVno_aFNBOHMxWGh_hQ | N91: ใช้เน็ตไม่ได้ | R91: ดำเนินการเรียบร้อย | S91: เสียบสาย lan และ Reboot เครื่องใช้งาน 1 ครั้ง สามารถต่อ wi-fi ใช้งานได้ปกติ | U91: IT02_ก๊อต | V91: ก่อนพัฒนา App
A92: 93 | B92: IT2410-091 | C92: 45580.696 | G92: 3769bd08 | H92: ปัญหาโปรแกรม | I92: Express | J92: อื่นๆ (โปรดระบุ) | N92: Express-mip บ้านแสงใช้งานไม่ได้ | R92: ดำเนินการเรียบร้อย | S92: Express-mip บ้านแสงใช้งานไม่ได้ server express boot ไม่พบระบบปฎิบัิติการ Set Bios เลือก boot Hard Disk สามารถใช้งาน express ได้ปกติ | U92: IT02_ก๊อต | V92: ก่อนพัฒนา App
A93: 95 | B93: IT2410-092 | C93: 45581.364 | D93: 30002 | E93: {=XLOOKUP(D93,Employee!A:A,Employee!D:D)&" "&XLOOKUP(D93,Employee!A:A,Employee!E:E)} | F93: Comets | G93: Ue03a410f57b81ccc708721f58c29836d | H93: ปัญหาโปรแกรม | I93: SAP | J93: ล็อคอินไม่ได้ | L93: PCM31_Kung | M93: https://profile.line-scdn.net/0hEsrzsmE3GlxfAwhW8ONkIy9TGTZ8ckNOd2UBOmxREDxhNF5ZIGMAPmkCTT4yMQkMczJQbmtRE2pTEG06QVXmaFgzR21jNFwPemRQuw | N93: เข้า SAP ไม่ได้ | O93: 192.168.202.97 | Q93: https://drive.google.com/file/d/1U4mEl2UHRDUYoknE003q60ebe82eX9Hi/view?usp=drivesdk | R93: ดำเนินการเรียบร้อย | S93: Reset password sap user id Pclnter1 new password : Comets2024 | U93: IT02_ก๊อต | V93: ก่อนพัฒนา App
A94: 96 | B94: IT2410-093 | C94: 45581.38 | D94: 10630 | E94: {=XLOOKUP(D94,Employee!A:A,Employee!D:D)&" "&XLOOKUP(D94,Employee!A:A,Employee!E:E)} | F94: Comets | G94: U119eab32108f3e09e260f57b4680ead7 | H94: ปัญหาโปรแกรม | I94: Email | J94: อีเมลเต็ม (แบ็คอัพอีเมล) | L94: Finance.acc_cm | M94: https://profile.line-scdn.net/0hOQt_9TSDEH5ZJgKmI7FuASl2ExR6V0lscEFZSmohTRxjEFcvcURZSDgmHktlE1V_JklXTGggS05VNWcYR3DsSl4WTU9lEVYtfEFamQ | N94: เมลเต็ม ย้ายไปBackup เหลือแค่ไม่กี่เมลเพราะต้องรอดำเนินการ ต้องแก้ไขตรงไหนเพิ่มไหมค่ะรบกวนแนะนำค่ะ | O94: 192.168.202.218 | R94: ดำเนินการเรียบร้อย | S94: User backupMail เหลือแค่ไม่กี่เฟส ตรวจสอบพื้นที่ zimbraAdmin fin@cometsintertrade.com Quota: 538.478 MB of 1,024 MB | T94: requests_Images/IT2410-096.photo.030033.jpg | U94: IT02_ก๊อต | V94: ก่อนพัฒนา App
A95: 97 | B95: IT2410-094 | C95: 45581.397 | D95: 11021 | E95: {=XLOOKUP(D95,Employee!A:A,Employee!D:D)&" "&XLOOKUP(D95,Employee!A:A,Employee!E:E)} | F95: Comets | G95: Ufa11ba9a84ed39a0fad801a6e50027c9 | H95: ปัญหาโปรแกรม | I95: Microsoft Office (Word, Excel, Power Point) | J95: ภาษาเพี้ยน | L95: Beam_i | M95: https://profile.line-scdn.net/0hRGbqVWxXDWhPCB2614xzFz9YDgJseVR6NzpDXS5bA1Fxak4_YWpBW3lYUFx3bUhrZmgQCSldVllDG3oOUV7xXEg4UFlzP0s7am9Hjw | N95: Excel เปิดไฟล์ CSV แล้วอ่านภาษาไทยไม่ออก | O95: 192.168.202.214 | Q95: https://drive.google.com/file/d/1y2d3Gd8tQvzLadj_uPWqdcvFQwW4aB4_/view?usp=drivesdk | R95: ดำเนินการเรียบร้อย | S95: ลง font ใหม่ และเปลี่ยน เปลี่ยน region current language for non-unicode programs thailand | T95: requests_Images/IT2410-097.photo.031626.jpg | U95: IT02_ก๊อต | V95: ก่อนพัฒนา App
A96: 98 | B96: IT2410-095 | C96: 45581.404 | D96: 30863 | E96: {=XLOOKUP(D96,Employee!A:A,Employee!D:D)&" "&XLOOKUP(D96,Employee!A:A,Employee!E:E)} | F96: ICT | G96: Uf783a285077fd96aea45bbafd50ce4b2 | H96: ปริ้นเตอร์ | I96: ปริ้นเตอร์อื่นๆ | J96: ปริ้นไม่ได้ | L96: J I R A Y U | M96: https://profile.line-scdn.net/0hejUMy5ZsOkV4NCqdFtlEOghkOS9bRWNXBwJ1Iks1YSBMUyhHUQAldEhnMXYQBy8VVlVwJ009YyB0J00jZmLGcX8EZ3REA3wWXVNwog | N96: VNC:192.168.102.92 | O96: เครื่องปริ้น ปริ้นไม่ได้ครับ | R96: ดำเนินการเรียบร้อย | S96: เชื่อมต่อปริ้นเตอร์ใหม่ | U96: IT03_วี | V96: ก่อนพัฒนา App
A97: 99 | B97: IT2410-096 | C97: 45581.411 | D97: 30435 | E97: {=XLOOKUP(D97,Employee!A:A,Employee!D:D)&" "&XLOOKUP(D97,Employee!A:A,Employee!E:E)} | F97: ICT | G97: U2c5e713b822099b6f2353a5cd859170f | H97: ปริ้นเตอร์ | I97: ปริ้นเตอร์อื่นๆ | J97: ปริ้นไม่ได้ | L97: 🐾Tipz🐾 | M97: https://profile.line-scdn.net/0hJg8wz0nhFUgVDgX7j9hrN2VeFiI2f0xaMGBde3cGGHh9bVFObj9SLSUPQ3p7agIba24NKyQOHC0ZHWIuC1jpfBI-SHkpOVMbMGlfrw | N97: ไม่สามารถปริ้นเอกสารของเครื่องปริ้น EPSON L3150 ได้ | O97: 192.168.103.171 | R97: ดำเนินการเรียบร้อย | S97: เชื่อมต่อปริ้นเตอร์ใหม่ | U97: IT03_วี | V97: ก่อนพัฒนา App
A98: 100 | B98: IT2410-097 | C98: 45581.412 | D98: 30611 | E98: {=XLOOKUP(D98,Employee!A:A,Employee!D:D)&" "&XLOOKUP(D98,Employee!A:A,Employee!E:E)} | F98: ICT | G98: U647cf4b56972406932aa5128c0a82eea | H98: ปริ้นเตอร์ | I98: ปริ้นเตอร์อื่นๆ | J98: ปริ้นไม่ได้ | L98: กวาง🦌💗💬✨️ | M98: https://profile.line-scdn.net/0hfTSi-fLXOXt-ECpwANpHBA5AOhFdYWBpUiV-G05CMB5BdHp5VH9zHkgWYUlFdH0pBSVxG0NHZExyA04dYEbFT3kgZEpCJ38oW3dznA | N98: ไม่สามารถปริ้นเตอร์ เครื่อง EPSON L3 150 QC ได้ค่ะ | O98: 192.168.103.179 | R98: ดำเนินการเรียบร้อย | S98: เชื่อมต่อปริ้นเตอร์ใหม่ | U98: IT03_วี | V98: ก่อนพัฒนา App
A99: 101 | B99: IT2410-098 | C99: 45581.432 | G99: 592cdaa2 | H99: ปัญหาเครือข่าย และอินเทอร์เน็ต | I99: อินเทอร์เน็ต | J99: ขอเชื่อมต่อ WiFi | N99: ใส่ Password Wi-Fi พนักงาน | R99: ดำเนินการเรียบร้อย | S99: ใส่ Password Wi-Fi พนักงาน FAC คุณมะเหมี่ยว, คุณแนน, คุณฟาง | U99: IT02_ก๊อต | V99: ก่อนพัฒนา App
A100: 102 | B100: IT2410-099 | C100: 45581.495 | G100: 6dd3356c | H100: ปัญหาโปรแกรม | I100: Email | J100: ยกเลิกอีเมล | N100: ยกเลิก FWD ของ EMAIL | R100: ดำเนินการเรียบร้อย | S100: ยกเลิก FWD ของ EMAIL PCM 03 -> salisa.p@cometsintertrade.com, pcm04@cometsintertrade.com | T100: requests_Images/IT2410-102.photo.045223.png | U100: IT02_ก๊อต | V100: ก่อนพัฒนา App
...

Sheet คู่มือ
A1: คู่มือ | B1: คู่มือ2
A2: คู่มือ_Images/3.คู่มือ.104438.jpg | B2: คู่มือ_Images/3.คู่มือ2.104438.jpg

Sheet Employee
A1: รหัสพนักงาน | B1: Password | C1: สังกัด | D1: ชื่อ(ไทย) | E1: นามสกุล(ไทย) | F1: (ไทย) ฝ่าย | G1: (ไทย) แผนก | H1: ตำแหน่ง(ไทย) | I1: ชื่อเล่น | J1: วันเริ่มงาน | K1: วันที่ออก | L1: อีเมล | M1: เบอร์โทร
A2: Admin | B2: 1234 | C2: Admin | D2: IT | E2: Admin | F2: Admin | G2: Admin | H2: Admin | I2: Admin
A3: 10001 | B3: 10001 | C3: Comets | D3: วรพล | E3: พิบูลย์สวัสดิ์ | F3: บริหาร | G3: A10_บริหาร | H3: A19_ประธานบริษัท | I3: คุณอู๋ | J3: 34239
A4: 10077 | B4: 10077 | C4: Comets | D4: ศุกร์วัน | E4: แซ่เจน | F4: บริหาร | G4: B21_เลขานุการ | H4: เลขานุการ | I4: ฟุ้ง | J4: 42373 | K4: 43856
A5: 10121 | B5: 10121 | C5: Comets | D5: ไชยวุฒิ | E5: เอี่ยมผ่องใส | F5: บริหาร | G5: A01 Executive | H5: รองประธานฝ่ายปฏิบัติการ | I5: พี่วุฒิ | J5: 42739 | K5: 43399
A6: 10002 | B6: 10002 | C6: Comets | D6: ศลิษา | E6: พิบูลย์สวัสดิ์ | F6: บริหาร | G6: A10_บริหาร | H6: A18_ประธานบริหาร | I6: คุณจุ๋ม | J6: 34239
A7: 10250 | B7: 10250 | C7: Comets | D7: สืบวงศ์ | E7: โรจน์วานิช | F7: บริหาร | G7: A01 Executive | H7: ประธานฝ่ายการตลาด | I7: สืบ | J7: 43040 | K7: 43185
A8: 10434 | B8: 10434 | C8: Comets | D8: ณัฐรินทร์ | E8: ตาลทอง | F8: บริหาร | G8: A01 Executive | H8: กรรมการบริษัท | I8: คุณเอ | J8: 43357 | K8: 43550
A9: 10435 | B9: 10435 | C9: Comets | D9: รุ่งราตรี | E9: เลิศพงศ์ไพศาล | F9: บริหาร | G9: A01 Executive | H9: - | I9: พี่ต้อม | J9: 43357 | K9: 43550
A10: 10436 | B10: 10436 | C10: Comets | D10: ชฎาธาร | E10: กันหอม | F10: บริหาร | G10: A01 Executive | H10: - | I10: พี่กุ้ง | J10: 43357 | K10: 43550
A11: 10450 | B11: 10450 | C11: Comets | D11: สืบสันติ์ | E11: ธนวิโรจน์กุล | F11: บริหาร | G11: A01 Executive | H11: - | I11: โบ๊ท | J11: 43389 | K11: 43550
A12: 10474 | B12: 10474 | C12: Comets | D12: สฤษฎ์รัช | E12: พิบูลย์สวัสดิ์ | F12: บริหาร | G12: A10_บริหาร | H12: B65_ผช.ผู้จัดการฝ่ายสารสนเทศ | I12: คุณโอม | J12: 43466 | K12: 44377
A13: 10483 | B13: 10483 | C13: Comets | D13: มานะ | E13: เตียงตระกูลทอง | F13: บริหาร | G13: A10_บริหาร | H13: A19_ที่ปรึกษาบริษัท | I13: คุณมานะ | J13: 43466 | K13: 44043
A14: 10120 | B14: 10120 | C14: Comets | D14: ณัทญา | E14: แซ่เตียว | F14: ฝ่ายการตลาด | G14: B14_ขับรถส่วนกลาง | H14: F12_เจ้าหน้าที่ผลิต อาวุโส | I14: ซู | J14: 42739 | K14: 43734
A15: 10190 | B15: 10190 | C15: Comets | D15: ยลรดี | E15: เปรมสมาน | F15: ฝ่ายการตลาด | G15: B21_เลขานุการ | H15: เลขานุการ | I15: ส้ม | J15: 42927 | K15: 43887
A16: 10485 | B16: 10485 | C16: Comets | D16: อุมารัตน์ | E16: ตฤษณารมย์ | F16: ฝ่ายการตลาด | G16: A21_การตลาด | H16: B26_ผช.ผู้จัดการฝ่ายการตลาด อาวุโส | I16: อุ | J16: 43497
A17: 10777 | B17: 10777 | C17: Comets | D17: รัตนา | E17: มีเทียน | F17: ฝ่ายการตลาด | G17: B11_ธุรการสำนักงาน | H17: F51_เจ้าหน้าที่ธุรการ | I17: อุ้ม | J17: 44768 | K17: 44770
A18: 10962 | B18: 10962 | C18: Comets | D18: กาญจิราณ์ | E18: มณีศิริ | F18: ฝ่ายการตลาด | G18: B11_ธุรการสำนักงาน | H18: CES1_เลขานุการผู้บริหาร | I18: อ้อม | J18: 45173 | K18: 45181
A19: 11003 | B19: 11003 | C19: Comets | D19: จินดารัตน์ | E19: หงส์พัฒนานุกุล | F19: ฝ่ายการตลาด | G19: B11_ธุรการสำนักงาน | H19: CES1_เลขานุการผู้บริหาร | I19: ลักกี้ | J19: 45294 | K19: 45351
A20: 11120 | B20: 11120 | C20: Comets | D20: ศกลวรรณ | E20: เอกนันทกุล | F20: ฝ่ายการตลาด | G20: A21_การตลาด | H20: B21_เจ้าหน้าที่ฝ่ายการตลาด | I20: นุ่น | J20: 45558
A21: 11126 | B21: 11126 | C21: Comets | D21: รัชฎา | E21: แดนวงดร | F21: ฝ่ายการตลาด | G21: A21_การตลาด | H21: B21_เจ้าหน้าที่ฝ่ายการตลาด | I21: บี | J21: 45572
A22: 11127 | B22: 11127 | C22: Comets | D22: จิราพร | E22: เสียงประเสริฐ | F22: ฝ่ายการตลาด | G22: A21_การตลาด | H22: B21_เจ้าหน้าที่ฝ่ายการตลาด | I22: ฝ้าย | J22: 45580 | K22: 45683
A23: 11162 | B23: 11162 | C23: Comets | D23: จิราพร | E23: ภู่ระหงษ์ | F23: ฝ่ายการตลาด | G23: A21_การตลาด | H23: B21_เจ้าหน้าที่ฝ่ายการตลาด | I23: โดนัท | J23: 45691 | K23: 45801
A24: 11163 | B24: 11163 | C24: Comets | D24: กัลยา | E24: ภู่จันทร์ | F24: ฝ่ายการตลาด | G24: A21_การตลาด | H24: B21_เจ้าหน้าที่ฝ่ายการตลาด | I24: เบียร์ | J24: 45691 | K24: 45801
A25: 11164 | B25: 11164 | C25: Comets | D25: อักษร | E25: ปราบพินาศ | F25: ฝ่ายการตลาด | G25: A21_การตลาด | H25: B23_หัวหน้าฝ่ายการตลาด | I25: เตย | J25: 45691
A26: 30890 | B26: 30890 | C26: Comets | D26: ลลิตา | E26: คุ้มครอง | F26: ฝ่ายการตลาด | G26: A21_การตลาด | H26: B21_เจ้าหน้าที่ฝ่ายการตลาด | I26: กิ่ง | J26: 45362 | K26: 45803
A27: 11258 | B27: 11258 | C27: Comets | D27: เบญจวรรณ | E27: สอนสา | F27: ฝ่ายการตลาด | G27: A21_การตลาด | H27: B21_เจ้าหน้าที่ฝ่ายการตลาด | I27: ปูเปรี้ยว | J27: 45903
A28: 11294 | B28: 11294 | C28: Comets | D28: รัฐภูมิเพชร | E28: เจ้าอภิบริบูรณ์ | F28: ฝ่ายการตลาด | G28: A21_การตลาด | H28: B21_เจ้าหน้าที่ฝ่ายการตลาด | I28: ภูมิ | J28: 45957
A29: 10496 | B29: 10496 | C29: Comets | D29: ชินเดช | E29: จงจิรจิต | F29: พัฒนาธุรกิจและกฏหมาย | G29: A03 Business Development&Law | H29: B85_ผช.ผู้จัดการฝ่ายขายนำเสนอสินค้า | I29: ชิน | J29: 43531 | K29: 43642
A30: 10078 | B30: 10078 | C30: Comets | D30: ปัทมา | E30: ผ่องไสยศรี | F30: บัญชีและการเงิน | H30: เจ้าหน้าที่บัญชี | I30: ฝน | J30: 42395 | K30: 43330
A31: 10080 | B31: 10080 | C31: Comets | D31: พัชรินทร์ | E31: พงษ์คุณ | F31: บัญชีและการเงิน | G31: A43_การเงิน | H31: B42_เจ้าหน้าที่การเงิน อาวุโส | I31: หน่อย | J31: 42415 | K31: 43307
A32: 10101 | B32: 10101 | C32: Comets | D32: บุณยนุช | E32: ขันทองดี | F32: บัญชีและการเงิน | H32: เจ้าหน้าที่บัญชี | I32: หยก | J32: 42527 | K32: 43307
A33: 10107 | B33: 10107 | C33: Comets | D33: ดารารัตน์ | E33: ธาราแดน | F33: บัญชีและการเงิน | H33: B46_ผช.ผู้จัดการบัญชีต้นทุน อาวุโส | I33: แหม่ม | J33: 42583 | K33: 43095
A34: 9031 | B34: 9031 | C34: Comets | D34: นพกานต์ | E34: เตชะศิริเชษฐ์ | F34: บัญชีและการเงิน | H34: หัวหน้าแผนก | J34: 42111 | K34: 42880
A35: 10110 | B35: 10110 | C35: Comets | D35: สุพรรษา | E35: วงศ์ษา | F35: บัญชีและการเงิน | H35: เจ้าหน้าที่บัญชี | I35: น้ำ | J35: 42604 | K35: 43250
A36: 10111 | B36: 10111 | C36: Comets | D36: จิราพร | E36: เหล็มกาศ | F36: บัญชีและการเงิน | H36: พนักงานบัญชี อาวุโส | J36: 42614 | K36: 43126
A37: 10016 | B37: 10016 | C37: Comets | D37: ศิริรัตน์ | E37: พรมแก้วต่อ | F37: บัญชีและการเงิน | H37: พนักงานบัญชี | I37: ติ๊ก | J37: 40513 | K37: 42919
A38: 10074 | B38: 10074 | C38: Comets | D38: เบญจรงค์ | E38: วงษ์สมัย | F38: บัญชีและการเงิน | G38: A41_บัญชี | H38: B41_เจ้าหน้าที่บัญชี | I38: อ้อ | J38: 42339
A39: 10173 | B39: 10173 | C39: Comets | D39: อรรถพร | E39: กิจสมัย | F39: บัญชีและการเงิน | G39: Finance_แผนกการเงิน | H39: เจ้าหน้าที่บัญชี | J39: 42887 | K39: 43039
A40: 10259 | B40: 10259 | C40: Comets | D40: ฐิติกานต์ | E40: บริบูรณ์ | F40: บัญชีและการเงิน | G40: A41_บัญชี | H40: B41_เจ้าหน้าที่บัญชี | I40: เปียร์ | J40: 43040 | K40: 43977
A41: 10268 | B41: 10268 | C41: Comets | D41: จิตรา | E41: รักษา | F41: บัญชีและการเงิน | H41: B46_ผช.ผู้จัดการฝ่ายการเงิน อาวุโส | I41: เจ เจ | J41: 43054 | K41: 43251
A42: 10275 | B42: 10275 | C42: Comets | D42: อรอนงค์ | E42: ศิริบุตร | F42: บัญชีและการเงิน | H42: เจ้าหน้าที่บัญชี | I42: แก้ว | J42: 43066 | K42: 43495
A43: 10279 | B43: 10279 | C43: Comets | D43: พนิดา | E43: จันทร์ทาแจ่ม | F43: บัญชีและการเงิน | H43: เจ้าหน้าที่บัญชี | I43: บี | J43: 43070 | K43: 43430
A44: 10281 | B44: 10281 | C44: Comets | D44: สุภาภรณ์ | E44: ด้วงพิบูลย์ | F44: บัญชีและการเงิน | G44: A43_การเงิน | H44: B42_เจ้าหน้าที่การเงิน อาวุโส | I44: ตูน | J44: 43075 | K44: 43313
A45: 10292 | B45: 10292 | C45: Comets | D45: ศิริรัตน์ | E45: พรมแก้วต่อ | F45: บัญชีและการเงิน | G45: A41_บัญชี | H45: B45_ผช.ผู้จัดการฝ่ายบัญชี | I45: ติ๊ก | J45: 43094
A46: 10295 | B46: 10295 | C46: Comets | D46: สุรางค์ | E46: เชิดตระกูล | F46: บัญชีและการเงิน | H46: B46_ผช.ผู้จัดการฝ่ายการเงิน อาวุโส | I46: นิว | J46: 43103 | K46: 43457
A47: 10333 | B47: 10333 | C47: Comets | D47: เรืองดาว | E47: ศุภจรจรัล | F47: บัญชีและการเงิน | H47: B46_ผช.ผู้จัดการฝ่ายบัญชี อาวุโส | I47: หลี | J47: 43171 | K47: 43218
A48: 10356 | B48: 10356 | C48: Comets | D48: ณัฏฐนันท์ | E48: กุลจิรัฐิติกาล | F48: บัญชีและการเงิน | G48: Accounting Costing | H48: B46_ผช.ผู้จัดการฝ่ายบัญชี อาวุโส | I48: นุ้ย | J48: 43235 | K48: 43764
A49: 10367 | B49: 10367 | C49: Comets | D49: ณัฐธพงษ์ | E49: ปัจจังคะถานัง | F49: บัญชีและการเงิน | H49: B64_หัวหน้าฝ่ายวิเคราะห์ข้อมูล อาวุโส | I49: พงษ์ | J49: 43255 | K49: 43342
A50: 10376 | B50: 10376 | C50: Comets | D50: กมลชนก | E50: เก่งมงคลธร | F50: บัญชีและการเงิน | H50: เจ้าหน้าที่บัญชี | I50: มดตะนอย | J50: 43277 | K50: 43324
A51: 10381 | B51: 10381 | C51: Comets | D51: เบญจมาส | E51: บุญศรีสมบัติ | F51: บัญชีและการเงิน | G51: A41_บัญชี | H51: B48_ผู้จัดการฝ่ายบัญชีและการเงิน | I51: เบญ | J51: 43283 | K51: 44807
A52: 10391 | B52: 10391 | C52: Comets | D52: กัลญาณี | E52: สินเสริฐ | F52: บัญชีและการเงิน | G52: A43_การเงิน | H52: B42_เจ้าหน้าที่การเงิน อาวุโส | I52: ตั๊ก | J52: 43297 | K52: 43554
A53: 10395 | B53: 10395 | C53: Comets | D53: กัลยา | E53: จำนงค์นารถ | F53: บัญชีและการเงิน | H53: B47_ผู้จัดการฝ่ายบัญชี | I53: กัน | J53: 43313 | K53: 43430
A54: 10397 | B54: 10397 | C54: Comets | D54: ตรีรัตน์ | E54: เพียพล | F54: บัญชีและการเงิน | H54: B45_ผช.ผู้จัดการฝ่ายการเงิน | I54: ป๊อป | J54: 43313 | K54: 43594
A55: 10407 | B55: 10407 | C55: Comets | D55: ศิริพร | E55: เอี่ยมละออ | F55: บัญชีและการเงิน | H55: B45_ผช.ผู้จัดการฝ่ายการเงิน | I55: ผักกาด | J55: 43313 | K55: 43352
A56: 10410 | B56: 10410 | C56: Comets | D56: นิลมล | E56: ธงชัย | F56: บัญชีและการเงิน | H56: B45_ผช.ผู้จัดการฝ่ายการเงิน | I56: กลอเรีย | J56: 43318 | K56: 43323
A57: 10411 | B57: 10411 | C57: Comets | D57: มณฑาทิพย์ | E57: กงซื่อ | F57: บัญชีและการเงิน | H57: B45_ผช.ผู้จัดการฝ่ายการเงิน | I57: ฮอล | J57: 43318 | K57: 43721
A58: 10415 | B58: 10415 | C58: Comets | D58: วรรณิศา | E58: สุหรั่งโรจน์ | F58: บัญชีและการเงิน | H58: B47_ผู้จัดการฝ่ายบัญชี | I58: ผึ้ง | J58: 43322 | K58: 43460
A59: 10472 | B59: 10472 | C59: Comets | D59: ชลกนก | E59: กวั้งซ้วน | F59: บัญชีและการเงิน | H59: B47_ผู้จัดการฝ่ายบัญชี | I59: สุ | J59: 43451 | K59: 43550
A60: 10473 | B60: 10473 | C60: Comets | D60: วรรวิษา | E60: อินทร์ห้อย | F60: บัญชีและการเงิน | G60: A41_บัญชี | H60: B47_ผู้จัดการฝ่ายบัญชี | I60: เปิ้ล | J60: 43467 | K60: 43831
A61: 10476 | B61: 10476 | C61: Comets | D61: ภัคสิตาพร | E61: อภิรักษ์สิทธิชน | F61: บัญชีและการเงิน | G61: A41_บัญชี | H61: B42_เจ้าหน้าที่บัญชี อาวุโส | I61: กิ๊ก | J61: 43472 | K61: 43887
A62: 10529 | B62: 10529 | C62: Comets | D62: เตือนใจ | E62: ภูแสงศรี | F62: บัญชีและการเงิน | G62: A43_การเงิน | H62: Senior Finance Officer | I62: น้ำหนึ่ง | J62: 43573 | K62: 43581
A63: 10586 | B63: 10586 | C63: Comets | D63: ณภษร | E63: มุงธิสาร | F63: บัญชีและการเงิน | G63: Accounting Costing | H63: พนักงานบัญชี | I63: พลอย | J63: 43710 | K63: 43797
A64: 10587 | B64: 10587 | C64: Comets | D64: ดาริกา | E64: ดีดอกไม้ | F64: บัญชีและการเงิน | G64: Accounting Costing | H64: B44_หัวหน้าฝ่ายบัญชี อาวุโส | I64: ดา | J64: 43710 | K64: 43793
A65: 10588 | B65: 10588 | C65: Comets | D65: วัลภา | E65: พัฒนสาร | F65: บัญชีและการเงิน | G65: A43_การเงิน | H65: B48_เจ้าหน้าที่การเงินอาวุโส | I65: เอ๋ | J65: 43717 | K65: 43919
A66: 10596 | B66: 10596 | C66: Comets | D66: กมลวรรณ | E66: มลิวัลย์ | F66: บัญชีและการเงิน | G66: Accounting Costing | H66: พนักงานบัญชี | I66: จุ๊บแจง | J66: 43745 | K66: 43779
A67: 10605 | B67: 10605 | C67: Comets | D67: ธนัชชา | E67: สื่อสุวรรณ์ | F67: บัญชีและการเงิน | G67: A41_บัญชี | H67: B45_ผช.ผู้จัดการฝ่ายบัญชี | I67: มิ้ง | J67: 43864 | K67: 44813
A68: 10610 | B68: 10610 | C68: Comets | D68: กรรณิกา | E68: วันสา | F68: บัญชีและการเงิน | G68: A43_การเงิน | H68: B81_เจ้าหน้าที่ธุรการขาย | I68: กรรณ | J68: 43913 | K68: 44191
A69: 10619 | B69: 10619 | C69: Comets | D69: สุณา | E69: หมื่นลูกท้าว | F69: บัญชีและการเงิน | G69: A41_บัญชี | H69: B42_เจ้าหน้าที่บัญชี อาวุโส | I69: อึ้ม | J69: 43997 | K69: 44100
A70: 10628 | B70: 10628 | C70: Comets | D70: ปุณยนุช | E70: กรุณา | F70: บัญชีและการเงิน | G70: Quality Control_แผนกพัฒนาบรรจุภัณฑ์Monthly | H70: B42_เจ้าหน้าที่การเงิน อาวุโส | I70: แอน | J70: 44179 | K70: 44184
A71: 10630 | B71: 10630 | C71: Comets | D71: วิภาพร | E71: ควรนาม | F71: บัญชีและการเงิน | G71: A43_การเงิน | H71: B43_หัวหน้าฝ่ายการเงิน | I71: เจี๊ยบ | J71: 44188
A72: 10657 | B72: 10657 | C72: Comets | D72: ญานิกา | E72: ชาบุญเรือง | F72: บัญชีและการเงิน | G72: A41_บัญชี | H72: B41_เจ้าหน้าที่บัญชี | I72: แอ๋ม | J72: 44354 | K72: 45001
A73: 10661 | B73: 10661 | C73: Comets | D73: ปิยธิดา | E73: ปัดถานัง | F73: บัญชีและการเงิน | G73: A41_บัญชี | H73: A17_ผู้อำนวยการฝ่ายการการเงิน&บัญชี | I73: น้ำว้า | J73: 44355 | K73: 44377
A74: 10795 | B74: 10795 | C74: Comets | D74: ธัญญ์จนัน | E74: ปิยอังกูรธรรม | F74: บัญชีและการเงิน | G74: A41_บัญชี | H74: B48_ผู้จัดการฝ่ายบัญชีและการเงิน | I74: จุ๊บ | J74: 44803 | K74: 44891
A75: 10801 | B75: 10801 | C75: Comets | D75: อโนมา | E75: วิชิตวรสาร | F75: บัญชีและการเงิน | G75: A41_บัญชี | H75: AAS3_หัวหน้าบัญชี | I75: โอ๋ | J75: 44837 | K75: 44987
A76: 10813 | B76: 10813 | C76: Comets | D76: สุปราณี | E76: คุ้มภัย | F76: บัญชีและการเงิน | G76: A41_บัญชี | H76: AAA5_ผู้ช่วยผู้จัดการฝ่ายบัญชีและการเงิน | I76: เล็ก | J76: 44866 | K76: 44923
A77: 10820 | B77: 10820 | C77: Comets | D77: ธนาภัสร์ | E77: อุดรปรีชา | F77: บัญชีและการเงิน | G77: A41_บัญชี | H77: B43_หัวหน้าฝ่ายบัญชี | I77: อุ๋ง | J77: 44915 | K77: 44983
A78: 10821 | B78: 10821 | C78: Comets | D78: ชลธิชา | E78: ศรีชาวนา | F78: บัญชีและการเงิน | G78: A41_บัญชี | H78: AAS3_หัวหน้าบัญชี | I78: ฝน | J78: 44915 | K78: 45084
A79: 10823 | B79: 10823 | C79: Comets | D79: กฤษฎา | E79: บุญเรือง | F79: บัญชีและการเงิน | G79: A41_บัญชี | H79: B48_ผู้จัดการฝ่ายบัญชีและการเงิน | I79: แบงค์ | J79: 44936 | K79: 45297
A80: 10824 | B80: 10824 | C80: Comets | D80: วราภร | E80: สุขารมณ์ | F80: บัญชีและการเงิน | G80: A41_บัญชี | H80: B46_ผช.ผู้จัดการฝ่ายบัญชี อาวุโส | I80: ภร | J80: 44936
A81: 10891 | B81: 10891 | C81: Comets | D81: พัชรีพร | E81: พรพิรุณโรจน์ | F81: บัญชีและการเงิน | G81: A41_บัญชี | H81: AAO1_เจ้าหน้าที่บัญชี | I81: ฝ้าย | J81: 45048 | K81: 45097
A82: 10899 | B82: 10899 | C82: Comets | D82: นัฐลดา | E82: กลึงกลิ่น | F82: บัญชีและการเงิน | G82: A41_บัญชี | H82: AAO1_เจ้าหน้าที่บัญชี | I82: นุ๊ก | J82: 45054 | K82: 45093
A83: 10941 | B83: 10941 | C83: Comets | D83: สิริประภา | E83: รอดภัยปวง | F83: บัญชีและการเงิน | G83: A41_บัญชี | H83: AAO1_เจ้าหน้าที่บัญชี | I83: ใบเฟิร์น | J83: 45110 | K83: 45408
A84: 10945 | B84: 10945 | C84: Comets | D84: เสาวนีย์ | E84: สุวรรณประเสริฐ | F84: บัญชีและการเงิน | G84: A41_บัญชี | H84: AAS3_หัวหน้าบัญชี | I84: เตย | J84: 45133 | K84: 45497
A85: 20021 | B85: 20021 | C85: Comets | D85: สุณา | E85: หมื่นลูกท้าว | F85: บัญชีและการเงิน | G85: A41_บัญชี | H85: B43_หัวหน้าฝ่ายบัญชี | I85: อึ้ม | J85: 43997
A86: 11038 | B86: 11038 | C86: Comets | D86: จิระพัชร์ | E86: จันทร์งาม | F86: บัญชีและการเงิน | G86: A41_บัญชี | H86: B48_ผู้จัดการฝ่ายบัญชีและการเงิน | I86: กล้วย | J86: 45383 | K86: 45493
A87: 11041 | B87: 11041 | C87: Comets | D87: ภัสส์ศา | E87: พรมเทศ | F87: บัญชีและการเงิน | G87: A43_การเงิน | H87: B41_เจ้าหน้าที่การเงิน | I87: ไอซ์ | J87: 45404
A88: 11243 | B88: 11243 | C88: Comets | D88: ณัฐวดี | E88: แซ่ลิ่ม | F88: บัญชีและการเงิน | G88: A43_การเงิน | H88: B41_เจ้าหน้าที่การเงิน | I88: บิว | J88: 45852
A89: 11246 | B89: 11246 | C89: Comets | D89: แก้วตา | E89: คำรศ | F89: บัญชีและการเงิน | G89: A41_บัญชี | H89: B41_เจ้าหน้าที่บัญชี | I89: ตุ๊กตา | J89: 45859 | L89: ap04@cometsintertrade.com | M89: 088-8968256
A90: 11265 | B90: 11265 | C90: Comets | D90: วันวิสา | E90: เสาวรส | F90: บัญชีและการเงิน | G90: A41_บัญชี | H90: B41_เจ้าหน้าที่บัญชี | I90: พิม | J90: 45923 | L90: cost02@cometsintertrade.com | M90: 988187182
A91: 11297 | B91: 11297 | C91: Comets | D91: อรพรรณ | E91: ผลงาม | F91: บัญชีและการเงิน | G91: A41_บัญชี | H91: B43_หัวหน้าฝ่ายบัญชี | I91: บี | J91: 45964
A92: 10128 | B92: 10128 | C92: Comets | D92: จริยา | E92: นาครทรรพ | F92: ทรัพยากรบุคคล | G92: Quality Control_แผนกตรวจสอบระหว่างการผลิต(แพ็ค)Daily | H92: B84_หัวหน้าธุรการฝ่ายขาย อาวุโส | I92: ปุ้ย | J92: 42761 | K92: 43307
A93: 10158 | B93: 10158 | C93: Comets | D93: ปราหนัน | E93: จักรทิพย์ | F93: ทรัพยากรบุคคล | G93: A51_ทรัพยากรบุคคล | H93: B54_หัวหน้าฝ่ายทรัพยากรบุคคล อาวุโส | I93: ยู | J93: 42828
A94: 10042 | B94: 10042 | C94: Comets | D94: ชญาดา | E94: สุตภักดี | F94: ทรัพยากรบุคคล | G94: A51_ทรัพยากรบุคคล | H94: B51_เจ้าหน้าที่ทรัพยากรบุคคล | I94: บ๋อมแบ๋ม | J94: 41828 | K94: 44426
A95: 10176 | B95: 10176 | C95: Comets | D95: กิตติ์ธเนศ | E95: เงินจินดาสุข | F95: ทรัพยากรบุคคล | G95: B14_ขับรถส่วนกลาง | H95: F52_เจ้าหน้าที่ขับรถผู้บริหาร อาวุโส | I95: ฤทธิ์ | J95: 42887 | K95: 43136
A96: 10177 | B96: 10177 | C96: Comets | D96: จักกฤช | E96: ชื่นกลิ่น | F96: ทรัพยากรบุคคล | G96: B14_ขับรถส่วนกลาง | H96: F52_เจ้าหน้าที่ขับรถผู้บริหาร อาวุโส | J96: 42887 | K96: 43098
A97: 9005 | B97: 9005 | C97: Comets | D97: อัญชิษฐา | E97: จงประทีป | F97: ทรัพยากรบุคคล | G97: - | H97: - | J97: 42373 | K97: 42792
A98: 10225 | B98: 10225 | C98: Comets | D98: จิตติมา | E98: จันทร์อุไร | F98: ทรัพยากรบุคคล | G98: Quality Control_แผนกตรวจสอบระหว่างการผลิต(แพ็ค)Daily | H98: เจ้าหน้าที่บุคคล | I98: ฝ้าย | J98: 42996 | K98: 43190
A99: 10293 | B99: 10293 | C99: Comets | D99: ฉัตรชัย | E99: พ่วงสุวรรณ | F99: ทรัพยากรบุคคล | G99: Quality Control_แผนกตรวจสอบระหว่างการผลิต(แพ็ค)Daily | H99: ผู้จัดการฝ่ายทรัพยากรบุคคล | I99: ฉัตร | J99: 43103 | K99: 43393
A100: 10304 | B100: 10304 | C100: Comets | D100: เก่ง | E100: งามแพง | F100: ทรัพยากรบุคคล | G100: B14_ขับรถส่วนกลาง | H100: F52_เจ้าหน้าที่ขับรถผู้บริหาร อาวุโส | I100: เก่ง | J100: 43115 | K100: 43525
...

Sheet Worklist
A1: jobType | B1: issueType | C1: อาการ
A2: คอมพิวเตอร์ | B2: Notebook | C2: หน้าจอฟ้า
A3: คอมพิวเตอร์ | B3: Notebook | C3: เครื่องเปิดไม่ติด
A4: คอมพิวเตอร์ | B4: Notebook | C4: เครื่องช้า
A5: คอมพิวเตอร์ | B5: Notebook | C5: Notebook ไม่เก็บไฟ
A6: คอมพิวเตอร์ | B6: Notebook | C6: ชาร์จไฟไม่เข้า
A7: คอมพิวเตอร์ | B7: Notebook | C7: ล็อกอินไม่ได้
A8: คอมพิวเตอร์ | B8: Notebook | C8: อื่นๆ (โปรดระบุ)
A9: คอมพิวเตอร์ | B9: PC | C9: หน้าจอฟ้า
A10: คอมพิวเตอร์ | B10: PC | C10: เครื่องเปิดไม่ติด
A11: คอมพิวเตอร์ | B11: PC | C11: เครื่องช้า
A12: คอมพิวเตอร์ | B12: PC | C12: ล็อกอินไม่ได้
... A162: ขอสิทธิ์เข้าระบบ (ทำใบขอสิทธิ์) | B162: พนักงานใหม่ | C162: อื่นๆ (โปรดระบุ)
A163: ขอสิทธิ์เข้าระบบ (ทำใบขอสิทธิ์) | B163: ขอสิทธิ์เข้าระบบ SAP
A164: ขอสิทธิ์เข้าระบบ (ทำใบขอสิทธิ์) | B164: ขอสิทธิ์เข้าระบบ Express
A165: ขอสิทธิ์เข้าระบบ (ทำใบขอสิทธิ์) | B165: เปลี่ยนแปลงสิทธิ์ (Driveshare) | C165: ขอเพิ่มสิทธิ์ไฟล์กลาง
A166: ขอสิทธิ์เข้าระบบ (ทำใบขอสิทธิ์) | B166: เปลี่ยนแปลงสิทธิ์ (Driveshare) | C166: ขอลบสิทธิ์ไฟล์กลาง
A167: ขอสิทธิ์เข้าระบบ (ทำใบขอสิทธิ์) | B167: เปลี่ยนแปลงสิทธิ์ (Driveshare) | C167: อื่นๆ (โปรดระบุ)
A168: ขอสิทธิ์เข้าระบบ (ทำใบขอสิทธิ์) | B168: เปลี่ยนแปลงสิทธิ์ (ปริ้นเตอร์) | C168: ขอเพิ่มสิทธิ์ปริ้นเตอร์ (สี)
A169: ขอสิทธิ์เข้าระบบ (ทำใบขอสิทธิ์) | B169: เปลี่ยนแปลงสิทธิ์ (ปริ้นเตอร์) | C169: ขอเพิ่มสิทธิ์ปริ้นเตอร์ (ขาว-ดำ)
A170: ขอสิทธิ์เข้าระบบ (ทำใบขอสิทธิ์) | B170: เปลี่ยนแปลงสิทธิ์ (ปริ้นเตอร์) | C170: อื่นๆ (โปรดระบุ)
A171: ขอสิทธิ์เข้าระบบ (ทำใบขอสิทธิ์) | B171: เปลี่ยนแปลงสิทธิ์ (Email) | C171: ขอเพิ่มอีเมล
A172: ขอสิทธิ์เข้าระบบ (ทำใบขอสิทธิ์) | B172: เปลี่ยนแปลงสิทธิ์ (Email) | C172: อื่นๆ (โปรดระบุ)
A173: ขอสิทธิ์เข้าระบบ (ทำใบขอสิทธิ์) | B173: ขอใช้งาน VPN
A174: ขอสิทธิ์เข้าระบบ (ทำใบขอสิทธิ์) | B174: เปลี่ยนแปลงสิทธิ์ (คอมพิวเตอร์) | C174: ขอเปลี่ยนคอมพิวเตอร์
A175: ขอสิทธิ์เข้าระบบ (ทำใบขอสิทธิ์) | B175: เปลี่ยนแปลงสิทธิ์ (คอมพิวเตอร์) | C175: ขอยืมคอมพิวเตอร์
A176: ขอสิทธิ์เข้าระบบ (ทำใบขอสิทธิ์) | B176: เปลี่ยนแปลงสิทธิ์ (คอมพิวเตอร์) | C176: อื่นๆ (โปรดระบุ)
A177: ขอสิทธิ์เข้าระบบ (ทำใบขอสิทธิ์) | B177: ขอใช้งานโปรแกรมอื่นๆ

Sheet Admin
A1: Admin | B1: Active
A2: IT01_ดุ่ย | B2: FALSE
A3: IT02_ก๊อต | B3: FALSE
A4: IT03_วี | B4: TRUE
A5: IT04_ปั้ม | B5: FALSE
A6: IT05_เอ็ม | B6: FALSE
A7: IT06_นุ | B7: FALSE
A8: IT07_ปุ๊ก | B8: TRUE
A9: IT08_แชมป์ | B9: TRUE
A10: IT09_ยาม้าล | B10: TRUE
